{"exactMatch": ["i96620"], "subject": ["Category:1594_births", "Category:1665_deaths", "Category:Premiers_peintres_du_Roi", "Category:Mythology_in_art", "Category:Paintings_by_Nicolas_Poussin", "Category:French_Baroque_painters", "Category:French_history_painters", "Category:People_from_Eure"], "subject__broader": ["Category:Ancien_R\u00e9gime_office-holders", "Category:French_painters", "Category:Court_painters", "Category:Works_based_on_mythology", "Category:Mythography", "Category:Visual_arts_by_subject", "Category:Mythology_in_popular_culture", "Category:Paintings_by_artist", "Category:French_paintings", "Category:Baroque_paintings", "Category:Baroque_painters", "Category:17th-century_French_painters", "Category:17th-century_French_art", "Category:French_Baroque_artists", "Category:French_painters_by_stylistic_period", "Category:History_painters", "Category:People_by_department_in_France", "Category:People_from_Normandy", "Category:Eure"], "subject__broader__broader": ["Category:Politicians_of_the_Ancien_R\u00e9gime_in_France", "Category:Offices_in_the_Ancien_R\u00e9gime", "Category:Political_office-holders_in_France", "Category:French_artists", "Category:Painters_by_nationality", "Category:Painters", "Category:Court_artists", "Category:Mythology", "Category:Works_based_on_folklore", "Category:Folklore_studies", "Category:Works_by_topic", "Category:Visual_arts", "Category:Works_of_art", "Category:Topics_in_the_arts", "Category:Topics_in_popular_culture", "Category:Antiquity_in_popular_culture", "Category:Mythology_by_culture", "Category:Works_by_artist", "Category:Paintings", "Category:French_art", "Category:Paintings_by_country", "Category:Baroque_painting", "Category:Baroque_art", "Category:Paintings_by_movement_or_period", "Category:Baroque_artists", "Category:Painters_by_period", "Category:17th-century_painters", "Category:French_painters_by_century", "Category:17th-century_French_people_by_occupation", "Category:17th-century_French_artists", "Category:Baroque_art_by_region", "Category:17th_century_in_art", "Category:Arts_and_culture_in_the_Ancien_R\u00e9gime", "Category:17th_century_in_France", "Category:French_Baroque", "Category:French_painters", "Category:Painters_by_theme", "Category:History_paintings", "Category:People_by_second-level_administrative_country_subdivision", "Category:Categories_by_department_of_France", "Category:French_people_by_location", "Category:Normandy", "Category:People_by_region_in_France", "Category:Departments_of_Normandy", "Category:Departments_of_France"], "subject__broader__related": ["Category:Sculptures_by_artist", "Category:War_artists", "Category:Normans"], "works": ["Et in Arcadia ego, 1637\u20131638"], "bot": ["InternetArchiveBot"], "caption": ["Self-portrait by Nicolas Poussin, 1650"], "date": ["October 2022"], "field": ["Painting"], "field__seeAlso": ["Outline_of_painting"], "field__seeAlso__seeAlso": ["Index_of_painting-related_articles"], "field__seeAlso__subject": ["Category:Lists_of_visual_art_topics", "Category:Outlines_of_culture_and_arts", "Category:Arts-related_lists", "Category:Wikipedia_outlines", "Category:Painting"], "field__subject": ["Category:Painting_techniques", "Category:Painting"], "field__subject__broader": ["Category:Artistic_techniques_by_art", "Category:Painting", "Category:Plastic_arts", "Category:Visual_arts_media", "Category:Art_by_type"], "field__hypernym": ["Practice"], "field__hypernym__wikiPageDisambiguates": ["Spiritual_practice", "The_Practice", "Practice_(learning_method)", "Practice-based_professional_learning", "The_Practice_(disambiguation)", "Practice_chanter", "Practice_theory", "Practice_of_law", "Best_practice", "Standards_and_Practices", "Legal_practice", "Phantom_practice"], "fixAttempted": ["yes"], "ref": ["none"], "wstitle": ["Poussin, Nicolas"], "movement": ["Classicism", "Baroque"], "movement__differentFrom": ["Classism"], "movement__differentFrom__wikiPageRedirects": ["Class_discrimination"], "movement__seeAlso": ["Classical_republicanism", "Earthquake_Baroque"], "movement__seeAlso__subject": ["Category:Republicanism", "Category:Earthquake_engineering", "Category:Baroque_architecture_in_the_Philippines", "Category:Baroque_architecture_in_the_Spanish_Empire", "Category:Baroque_architectural_styles"], "movement__seeAlso__hypernym": ["Form", "Style"], "movement__seeAlso__url": ["index.php%3Fid=1673"], "movement__seeAlso__date": [2020], "movement__subject": ["Category:Art_movements", "Category:Theories_of_aesthetics", "Category:Classicism", "Category:Early_Modern_period", "Category:Art_movements_in_Europe", "Category:17th_century_in_the_arts", "Category:18th_century_in_the_arts", "Category:18th_century_in_art", "Category:Catholic_art_by_period", "Category:Catholic_art", "Category:17th_century_in_art", "Category:Baroque", "Category:Decorative_arts"], "movement__subject__broader": ["Category:Art_history", "Category:Movements", "Category:Style", "Category:Aesthetics", "Category:Philosophical_theories", "Category:Art_movements", "Category:Theories_of_aesthetics", "Category:Western_culture", "Category:2nd_millennium", "Category:Historical_eras", "Category:Modern_history", "Category:European_art", "Category:Art_movements_by_continent", "Category:Movements_in_Europe", "Category:17th_century", "Category:Arts_by_century", "Category:2nd_millennium_in_the_arts", "Category:18th_century", "Category:Art_by_century", "Category:18th_century_in_the_arts", "Category:18th-century_works", "Category:Catholic_art", "Category:Art_by_period_of_creation", "Category:Catholic_culture", "Category:Medieval_art", "Category:Arts_by_culture", "Category:Christian_art_by_denomination", "Category:17th_century_in_the_arts", "Category:17th-century_works", "Category:Early_Modern_period", "Category:18th_century_in_art", "Category:17th_century_in_art", "Category:Visual_arts_genres"], "noprescript": [1], "movement__exactMatch": ["i117432"], "movement__caption": ["Fa\u00e7ade of the Jesuit Church of Arequipa , 1698\u20131699, by Diego de Adri\u00e1n and others", "Preserved colonial wall painting of 1802 depicting Hell, by Tadeo Escalante, inside the Church of San Juan Bautista in Huaro", "Top:  Venus and Adonis by Peter Paul Rubens ; Centre: The Ecstasy of Saint Teresa by Bernini ; Bottom: The Palace of Versailles in France"], "movement__totalWidth": [300, 450], "movement__footer": ["Various French Baroque ornaments and architectural elements", "St. Peter's Basilica , completed in 1615, by Donato Bramante, Michelangelo, Carlo Maderno and others", "Karlskirche, Vienna, Austria, 1715-1737, by Johann Bernhard Fischer von Erlach"], "movement__perrow": [1, 3], "movement__countries": ["Europe and Latin America"], "movement__date": ["December 2019", "April 2020"], "movement__align": ["right"], "movement__width": [190], "movement__direction": ["vertical"], "movement__yearsactive": [17], "movement__reason": ["How can this apply to music or gardens?", "why would scholars \"point\" to a Latin word that cannot possibly be the source of the Portuguese?"], "notableWork": ["Et_in_Arcadia_ego"], "notableWork__homepage": ["arcadia.htm"], "notableWork__subject": ["Category:Iconography", "Category:Paintings_in_the_Louvre_by_French_artists", "Category:Latin_mottos", "Category:Priory_of_Sion_hoax", "Category:Paintings_by_Nicolas_Poussin", "Category:Greek_mythology_studies", "Category:Ancient_Arcadia", "Category:Paintings_about_death", "Category:Ancient_Greece_in_art_and_culture"], "notableWork__subject__broader": ["Category:Art_history", "Category:French_paintings", "Category:Paintings_in_the_collection_of_the_Louvre", "Category:Mottos", "Category:Latin_words_and_phrases", "Category:Latin_quotations", "Category:Fictional_secret_societies", "Category:Bible_conspiracy_theories", "Category:Western_esotericism", "Category:Historical_negationism", "Category:Hoaxes_in_France", "Category:Knights_Templar_in_popular_culture", "Category:1960s_hoaxes", "Category:Pseudohistory", "Category:Paintings_by_artist", "Category:Baroque_paintings", "Category:Mythology", "Category:Ancient_Greece_studies", "Category:History_of_Arcadia,_Peloponnese", "Category:Ancient_Peloponnese", "Category:Death_in_art", "Category:Paintings_by_subject", "Category:Places_in_popular_culture", "Category:Classical_antiquity_in_modern_art_and_culture", "Category:Ancient_Greece"], "notableWork__title": ["Et in Arcadia ego"], "notableWork__hypernym": ["Painting"], "notableWork__hypernym__seeAlso": ["Outline_of_painting"], "notableWork__hypernym__subject": ["Category:Painting_techniques", "Category:Painting"], "notableWork__hypernym__hypernym": ["Practice"], "notableWork__widthImperial": [47.24], "notableWork__heightMetric": [85], "notableWork__widthMetric": [121], "notableWork__heightImperial": [34.25], "notableWork__medium": ["oil on canvas"], "notableWork__artist": ["Nicolas_Poussin"], "notableWork__artist__exactMatch": ["i96620"], "notableWork__artist__subject": ["Category:1594_births", "Category:1665_deaths", "Category:Premiers_peintres_du_Roi", "Category:Mythology_in_art", "Category:Paintings_by_Nicolas_Poussin", "Category:French_Baroque_painters", "Category:French_history_painters", "Category:People_from_Eure"], "notableWork__artist__works": ["Et in Arcadia ego, 1637\u20131638"], "notableWork__artist__bot": ["InternetArchiveBot"], "notableWork__artist__caption": ["Self-portrait by Nicolas Poussin, 1650"], "notableWork__artist__date": ["October 2022"], "notableWork__artist__field": ["Painting"], "notableWork__artist__fixAttempted": ["yes"], "notableWork__artist__ref": ["none"], "notableWork__artist__wstitle": ["Poussin, Nicolas"], "notableWork__artist__movement": ["Classicism", "Baroque"], "notableWork__artist__noprescript": [1], "notableWork__artist__notableWork": ["Et_in_Arcadia_ego"], "notableWork__artist__hypernym": ["Painter"], "notableWork__year": [1637], "notableWork__museum": ["Mus\u00e9e du Louvre"], "notableWork__metricUnit": ["cm"], "notableWork__imperialUnit": ["in"], "notableWork__author": ["Nicolas_Poussin"], "notableWork__author__exactMatch": ["i96620"], "notableWork__author__subject": ["Category:1594_births", "Category:1665_deaths", "Category:Premiers_peintres_du_Roi", "Category:Mythology_in_art", "Category:Paintings_by_Nicolas_Poussin", "Category:French_Baroque_painters", "Category:French_history_painters", "Category:People_from_Eure"], "notableWork__author__works": ["Et in Arcadia ego, 1637\u20131638"], "notableWork__author__bot": ["InternetArchiveBot"], "notableWork__author__caption": ["Self-portrait by Nicolas Poussin, 1650"], "notableWork__author__date": ["October 2022"], "notableWork__author__field": ["Painting"], "notableWork__author__fixAttempted": ["yes"], "notableWork__author__ref": ["none"], "notableWork__author__wstitle": ["Poussin, Nicolas"], "notableWork__author__movement": ["Classicism", "Baroque"], "notableWork__author__noprescript": [1], "notableWork__author__notableWork": ["Et_in_Arcadia_ego"], "notableWork__author__hypernym": ["Painter"], "notableWork__imageFile": ["Nicolas Poussin - Et in Arcadia ego .jpg"], "notableWork__otherTitle": ["Les Bergers d'Arcadie"], "hypernym": ["Painter"], "hypernym__wikiPageRedirects": ["Painting"], "hypernym__wikiPageRedirects__seeAlso": ["Outline_of_painting"], "hypernym__wikiPageRedirects__subject": ["Category:Painting_techniques", "Category:Painting"], "hypernym__wikiPageRedirects__hypernym": ["Practice"]}