{"subject": ["Category:1723_births", "Category:Painters_from_Verona", "Category:18th-century_Italian_painters", "Category:1797_deaths", "Category:Italian_male_painters", "Category:Accidental_deaths_from_falls", "Category:18th-century_Italian_people", "Category:Rococo_painters"], "subject__broader": ["Category:History_of_Verona", "Category:Artists_from_Verona", "Category:Italian_painters_by_city", "Category:18th-century_Italian_artists", "Category:18th-century_Italian_people_by_occupation", "Category:Italian_painters_by_century", "Category:18th-century_painters", "Category:Italian_painters", "Category:Italian_male_artists", "Category:Male_painters_by_nationality", "Category:Deaths_from_falls", "Category:Accidental_deaths", "Category:Italian_people_by_century", "Category:18th-century_European_people_by_nationality", "Category:18th_century_in_Italy", "Category:18th-century_people_by_nationality", "Category:Painters_by_period", "Category:Rococo_artists"], "subject__broader__broader": ["Category:History_of_Veneto", "Category:Histories_of_cities_in_Italy", "Category:Verona", "Category:People_from_Verona", "Category:Italian_artists_by_city_or_town", "Category:Italian_painters", "Category:Italian_people_by_occupation_and_city", "Category:Painters_by_city", "Category:18th-century_artists_by_nationality", "Category:18th-century_Italian_people_by_occupation", "Category:Italian_artists_by_century", "Category:Italian_people_by_century_and_occupation", "Category:18th-century_Italian_people", "Category:18th-century_people_by_nationality_and_occupation", "Category:Italian_people_by_occupation_and_century", "Category:Painters_by_century", "Category:18th-century_artists", "Category:Male_artists_by_nationality", "Category:Italian_men_by_occupation", "Category:Italian_artists", "Category:Male_painters", "Category:Painters_by_nationality", "Category:Falling", "Category:Deaths_by_cause", "Category:Accidents", "Category:European_people_by_century", "Category:Italian_people_by_period", "Category:People_by_nationality_and_century", "Category:European_people_by_nationality", "Category:18th-century_European_people", "Category:18th-century_people_by_nationality", "Category:2nd_millennium_in_Italy", "Category:18th_century_by_country", "Category:18th_century_in_Europe", "Category:Centuries_in_Italy", "Category:Artists_by_period", "Category:Painters", "Category:People_by_occupation_and_period", "Category:Rococo_art"], "subject__related": ["Category:Mountaineering_deaths", "Category:Deaths_in_sport", "Category:Deaths_by_horse-riding_accident"], "subject__related__broader": ["Category:Deaths_in_sport", "Category:Mountaineering", "Category:Mountaineering_and_health", "Category:Sports-related_accidents_and_incidents", "Category:Sports", "Category:Deaths_by_cause", "Category:Deaths_from_falls", "Category:Horse-related_accidents_and_incidents", "Category:Accidental_deaths"], "hypernym": ["Painter"], "hypernym__wikiPageRedirects": ["Painting"], "hypernym__wikiPageRedirects__seeAlso": ["Outline_of_painting"], "hypernym__wikiPageRedirects__subject": ["Category:Painting_techniques", "Category:Painting"], "hypernym__wikiPageRedirects__hypernym": ["Practice"]}