{"seeAlso": ["Art", "1952"], "seeAlso__seeAlso": ["Artistic_skill", "Conceptual_art"], "seeAlso__seeAlso__differentFrom": ["Concept_art", "Philosophical_conceptualism"], "seeAlso__seeAlso__homepage": [""], "seeAlso__seeAlso__subject": ["Category:Aesthetics", "Category:Conceptualism", "Category:Contemporary_art_movements", "Category:Conceptual_art", "Category:Postmodern_art", "Category:Visual_arts_media"], "seeAlso__seeAlso__hypernym": ["Art"], "seeAlso__subject": ["Category:Aesthetics", "Category:Visual_arts", "Category:Art", "Category:The_arts", "Category:Leap_years_in_the_Gregorian_calendar", "Category:1952"], "seeAlso__subject__broader": ["Category:Perception", "Category:The_arts", "Category:Branches_of_philosophy", "Category:Vision", "Category:Skills", "Category:Arts_by_type", "Category:Aesthetics", "Category:Visual_arts", "Category:Creativity", "Category:Human_activities", "Category:Humanities", "Category:Culture", "Category:Years", "Category:Gregorian_calendar"], "seeAlso__hypernym": ["Range", "Year"], "seeAlso__hypernym__wikiPageDisambiguates": ["Heidi_Range", "Shooting_range", "Range:_Why_Generalists_Triumph_in_a_Specialized_World", "Range,_Alabama", "Range,_Ohio", "Driving_range", "Range_(music)", "Range_(aeronautics)", "Bombing_range", "M._Athalie_Range", "Rangefinder", "Range_(computer_programming)", "Range_anxiety", "Range,_Wisconsin", "Range_of_a_projectile", "Vocal_range", "Projective_range", "Slant_range", "All-electric_range", "Rosslyn_Range", "Range_(geographic)", "Ranger_(disambiguation)", "The_Range_(disambiguation)", "Erik_Range", "Range_factor", "Range_(biology)", "Rangeland", "Range_(statistics)", "Harald_Range", "Range_of_a_function", "Range_(particle_radiation)", "Mountain_range"], "seeAlso__small": ["no"], "seeAlso__colwidth": [20], "seeAlso__by": ["no"], "seeAlso__others": ["no"], "seeAlso__about": ["yes"], "seeAlso__onlinebooks": ["no"], "seeAlso__hypernym__seeAlso": ["Astronomical_month"], "seeAlso__hypernym__subject": ["Category:Types_of_year"], "seeAlso__hypernym__hypernym": ["Period"], "subject": ["Category:1952_in_the_Soviet_Union", "Category:Soviet_art", "Category:1952_in_art"], "subject__broader": ["Category:European_art", "Category:20th_century_in_art", "Category:Russian_art", "Category:Arts_in_the_Soviet_Union", "Category:Works_by_Soviet_people", "Category:Art_by_country"], "subject__broader__broader": ["Category:Western_art", "Category:Arts_in_Europe", "Category:Art_by_continent", "Category:Art_by_century", "Category:20th_century_in_the_arts", "Category:20th-century_works", "Category:Works_by_Russian_people", "Category:Arts_in_Russia", "Category:European_art_by_country", "Category:Art_by_country", "Category:Asian_art_by_country", "Category:Soviet_culture", "Category:Arts_by_former_country", "Category:Arts_in_Asia", "Category:Works_by_nationality", "Category:Arts_in_the_Soviet_Union", "Category:Art", "Category:Visual_arts_by_location", "Category:Arts_genres_by_country_or_nationality"], "subject__broader__related": ["Category:Arts_by_country"], "title": ["Monument to Nikolai Gogol", "Monument to Nikolai Rimsky-Korsakov"], "city": ["Saint_Petersburg", "Moscow"], "city__seeAlso": ["Academic_institutions", "List_of_higher_education", "Saint_Petersburg", "Sister_cities", "List_of_twin_towns", "Russia", "Timeline_of_Saint_Petersburg", "Rail_transport", "List_of_shopping_malls", "List_of_tallest_buildings", "Carsharing", "Government_of_Moscow", "Media_of_Russia", "Hotels", "White_House_(Moscow)", "List_of_Moscow_tourist_attractions", "Television", "Moscow", "Ethnic_groups", "Economy_of_Russia", "Football"], "city__seeAlso__wikiPageRedirects": ["Academic_institution", "Sister_city", "Lists_of_twin_towns_and_sister_cities", "Lists_of_shopping_malls", "Mass_media_in_Russia", "Hotel", "List_of_tourist_attractions_in_Moscow", "Ethnic_group"], "city__seeAlso__seeAlso": ["Academic_institutions", "List_of_higher_education", "Saint_Petersburg", "Sister_cities", "List_of_twin_towns", "Russia", "Timeline_of_Saint_Petersburg", "Rail_transport", "Proto-Indo-Europeans", "Timeline_of_Russian_innovation", "Russian_cuisine", "Moscow", "Third_Rome", "List_of_ecoregions", "History_of_Saint_Petersburg", "Diesel_locomotive", "Steam_locomotive", "Funicular", "Electric_locomotive", "Heritage_railways", "Countries", "Television_show", "Digital_television_transition", "Cable_television_by_region", "TV_listings_(UK)", "Timeline_of_the_introduction_of_television", "List_of_shopping_malls", "List_of_tallest_buildings", "Carsharing", "Government_of_Moscow", "Media_of_Russia", "Hotels", "White_House_(Moscow)", "List_of_Moscow_tourist_attractions", "Television", "Ethnic_groups", "Economy_of_Russia", "Football", "Federal_budget_of_Russia", "Economic_impact_of_the_2022_Russian_invasion_of_Ukraine", "List_of_countries_by_natural_gas_proven_reserves", "Episkyros", "Rugby_league", "Gaelic_football", "Origins_of_Australian_rules_football", "Comparison_of_American_football", "Comparison_of_Australian_rules_football"], "city__seeAlso__homepage": ["", "index_en.html", "en"], "city__seeAlso__exactMatch": ["i84008", "i84732", "i83988", "i84002", "17534-6", "13655-0", "i83991"], "city__seeAlso__lat": [59.9375, 55.75583267211914, 59.95000076293945, 55.75493621826172], "city__seeAlso__long": [30.3086109161377, 37.61722183227539, 30.29999923706055, 37.57314682006836], "city__seeAlso__subject": ["Category:Former_national_capitals", "Category:Port_cities_and_towns_of_the_Baltic_Sea", "Category:Port_cities_and_towns_in_Russia", "Category:1703_establishments_in_Europe", "Category:Populated_coastal_places_in_Russia", "Category:Federal_cities_of_Russia", "Category:1703_establishments_in_Russia", "Category:World_Heritage_Sites_in_Russia", "Category:Saint_Petersburg", "Category:Populated_places_established_in_1703", "Category:Sankt-Peterburgsky_Uyezd", "Category:Planned_capitals", "Category:Member_states_of_the_United_Nations", "Category:Christian_states", "Category:Russia", "Category:E7_nations", "Category:Russian-speaking_countries_and_territories", "Category:1991_establishments_in_Europe", "Category:North_Asian_countries", "Category:Countries_in_Europe", "Category:Observer_states_of_the_Organisation_of_Islamic_Cooperation", "Category:Eastern_European_countries", "Category:BRICS_nations", "Category:Federal_republics", "Category:Member_states_of_the_Shanghai_Cooperation_Organisation", "Category:Transcontinental_countries", "Category:1991_establishments_in_Asia", "Category:Countries_in_Asia", "Category:Member_states_of_the_Commonwealth_of_Independent_States", "Category:States_and_territories_established_in_1991", "Category:G20_nations", "Category:Northeast_Asian_countries", "Category:History_of_Saint_Petersburg", "Category:Saint_Petersburg-related_lists", "Category:Timelines_of_cities_in_Russia", "Category:Years_in_Russia", "Category:Infrastructure", "Category:Rail_transport", "Category:Transportation_engineering", "Category:Lists_of_tallest_buildings", "Category:Skyscrapers", "Category:Lists_of_construction_records", "Category:Lists_of_buildings_and_structures", "Category:Sustainable_transport", "Category:Carsharing", "Category:Government_of_Moscow", "Category:Politics_of_Moscow", "Category:Articles_containing_video_clips", "Category:Former_seats_of_national_legislatures", "Category:1981_establishments_in_Russia", "Category:Legislative_buildings_in_Europe", "Category:Buildings_and_structures_completed_in_1981", "Category:Buildings_and_structures_in_Moscow", "Category:Government_buildings_in_Russia", "Category:German_inventions", "Category:British_inventions", "Category:Russian_inventions", "Category:Media_formats", "Category:Digital_technology", "Category:Broadcasting", "Category:Advertising_by_medium", "Category:20th-century_inventions", "Category:1925_introductions", "Category:Video_hardware", "Category:1925_in_technology", "Category:1927_in_technology", "Category:1927_introductions", "Category:Television_industry", "Category:Telecommunications-related_introductions_in_1925", "Category:Telecommunications-related_introductions_in_1927", "Category:Television", "Category:Television_terminology", "Category:Performing_arts", "Category:Consumer_electronics", "Category:American_inventions", "Category:Capitals_in_Europe", "Category:Populated_places_established_in_the_12th_century", "Category:Moskovsky_Uyezd", "Category:12th-century_establishments_in_Russia", "Category:Moscow", "Category:Economy_of_Russia", "Category:World_Trade_Organization_member_economies", "Category:Economies_of_Europe_by_country", "Category:Sports_culture", "Category:Ball_games", "Category:Broad-concept_articles", "Category:Football", "Category:Summer_sports"], "city__seeAlso__website": ["", "en"], "city__seeAlso__id": [540], "city__seeAlso__title": ["Religion in Saint Petersburg as of 2012", "Articles related to Saint Petersburg", "Ethnic groups across Russia", "Minority languages across Russia", "Articles related to Russia", "Frequently Asked Questions on Energy Security", "World cities by carshare fleet in 2018", "Religion in Moscow"], "city__seeAlso__caption": ["Catherine Palace in Tsarskoe Selo", "Vladimir_Putin", "Mikhail_Mishustin", "(Prime Minister)", "Altaic and Uralic languages spoken across Russia", "(President)", "The North Caucasus is ethno-linguistically diverse.", null, "Population of Moscow by year", "The Moscow International Business Center", "Sheffield F.C.  is the oldest surviving association football club in the world"], "city__seeAlso__point": ["59.9375 30.308611111111112", "55.755833333333335 37.617222222222225", "59.95 30.3", "55.754935 37.573146"], "city__seeAlso__hypernym": ["City", "State", "Timeline", "Means", "Body", "Building", "Medium", "Capital", "Family"], "city__seeAlso__foundingDate": [1703], "city__seeAlso__imageCaption": ["Top-down, left-to-right: The Winter Palace; Palace Bridge; Peter and Paul Cathedral; Saint Isaac's Cathedral; the General Staff Building; the Moyka River from the Pevchesky Bridge to the Red Bridge", "The building in 2016"], "city__seeAlso__criteria": [", , ,"], "city__seeAlso__imageCoa": ["Coat of Arms of Saint Petersburg .svg"], "city__seeAlso__coaCaption": ["Coat_of_Arms_of_Saint_Petersburg"], "city__seeAlso__areaKm2Rank": [82], "city__seeAlso__politicalStatus": ["Federal city"], "city__seeAlso__licensePlates": [7898178198], "city__seeAlso__economicRegion": ["Northwestern_economic_region"], "city__seeAlso__flagCaption": ["Flag_of_Saint_Petersburg"], "city__seeAlso__politicalStatusLink": ["Federal cities of Russia"], "city__seeAlso__federalDistrict": ["Northwestern_Federal_District"], "city__seeAlso__enName": ["Saint Petersburg"], "city__seeAlso__ruName": ["\u0421\u0430\u043d\u043a\u0442-\u041f\u0435\u0442\u0435\u0440\u0431\u0443\u0440\u0433"], "city__seeAlso__height": [397, 400, 422, 508, 119, "119 m", 175], "city__seeAlso__url": ["%3Flang=en", "moscow-housing-map"], "city__seeAlso__establishedTitle": ["Founded", "First mentioned"], "city__seeAlso__establishedDate": [1703, 879, 1157, 1263, 1991, 1990, 1917, 1993, 1721, 1999, 1922, 1547, 1147], "city__seeAlso__r": ["Sankt-Peterburg", "Moskva"], "city__seeAlso__totalWidth": [350, 230, 300, 400, 200, 250, 600], "city__seeAlso__anthem": ["Anthem_of_Saint_Petersburg", "File:\u0413\u0438\u043c\u043d_\u0421\u0430\u043d\u043a\u0442-\u041f\u0435\u0442\u0435\u0440\u0431\u0443\u0440\u0433\u0430.ogg", "State_Anthem_of_the_Russian_Federation", "Moya_Moskva", "\"My Moscow\""], "city__seeAlso__p": ["\u02c8sankt p\u02b2\u026at\u02b2\u026ar\u02c8burk", "m\u0250sk\u02c8va"], "city__seeAlso__float": ["left", "center", "right"], "city__seeAlso__footer": ["Clockwise from left: Kronstadt: the Naval Cathedral on Yakornaya Square; the Church of St. Catherine; the Saint Petersburg Mosque; and the Grand Choral Synagogue of St. Petersburg", "Left: Railway turnouts; Right: Chicago Transit Authority control box guides elevated Chicago 'L' north and southbound Purple and Brown lines intersecting with east and westbound Pink and Green lines and the looping Orange line above the Wells and Lake street intersection in the loop at an elevated right of way.", "The Bolshoi Theatre", "Clockwise from left: The Cathedral of Christ the Saviour, demolished during the Soviet period and reconstructed from 1990\u20132000; Cathedral of the Immaculate Conception; Moscow Cathedral Mosque; and Moscow Choral Synagogue", "Several codes of football. Clockwise from top left: association, gridiron, rugby union, Gaelic, rugby league, and Australian rules", "The action of kicking in  association, gridiron, Australian and rugby football", "The first football international, Scotland versus England. Once kept by the Rugby Football Union as an early example of rugby football."], "city__seeAlso__perrow": [2, 4], "city__seeAlso__imageUpright": [1.2], "city__seeAlso__extension": [2013], "city__seeAlso__geometry": [null], "city__seeAlso__officialName": ["Historic Centre of Saint Petersburg and Related Groups of Monuments"], "city__seeAlso__country": ["Russia", "Soviet Union"], "city__seeAlso__imageFlag": ["Flag of Saint Petersburg Russia.svg", "Flag of Russia.svg", "Flag of Moscow.svg", "Flag of Moscow, Russia.svg"], "city__seeAlso__year": [1990, "calendar year"], "city__seeAlso__areaKm": [1439, 17098246], "city__seeAlso__leaderTitle": ["Governor", "Governor_of_Saint_Petersburg", "Chairman_of_the_Federation_Council_(Russia)", "Chairman_of_the_State_Duma", "Chief_Justice_of_the_Russian_Federation", "Prime_Minister_of_Russia", "President_of_Russia", "Head", "Mayor_of_Moscow"], "city__seeAlso__areaTotal": [null, 1439000000, 2561498241.122304, 2561500000], "city__seeAlso__imageMap": ["Russia Saint Petersburg locator map.svg", "Russian Federation  - Annexed Territories disputed.svg", "Russia Moscow locator map.svg"], "city__seeAlso__leaderName": ["Alexander Beglov", "Alexander_Beglov", "Vladimir_Putin", "Vyacheslav_Volodin", "Vyacheslav_Mikhailovich_Lebedev", "Mikhail_Mishustin", "Valentina_Matviyenko", "Sergey_Sobyanin", null], "city__seeAlso__date": ["October 2018", "November 2021", 2014, "June 2022", "November 2022", 2020, "January 2021", "January 2011"], "city__seeAlso__align": ["right", "left", "center"], "city__seeAlso__width": [500, 560, 595, 177, 200, 795, 530, 1250, 2230], "city__seeAlso__links": ["no"], "city__seeAlso__iso": ["RU-SPE"], "city__seeAlso__a": ["Ru-Sankt Peterburg Leningrad Petrograd Piter.ogg", "\u041c\u043e\u0441\u043a\u0432\u0430.ogg"], "city__seeAlso__certain": ["y"], "city__seeAlso__legislature": ["Legislative_Assembly_of_Saint_Petersburg", "Federal_Assembly_(Russia)"], "city__seeAlso__upperHouse": ["Federation_Council_(Russia)"], "city__seeAlso__lowerHouse": ["State_Duma"], "city__seeAlso__hdiChange": ["increase"], "city__seeAlso__largestCity": ["capital"], "city__seeAlso__drivesOn": ["right"], "city__seeAlso__callingCode": ["Telephone_numbers_in_Russia"], "city__seeAlso__hdiRank": [52], "city__seeAlso__isPartOf": ["target"], "city__seeAlso__populationDensity": [8.301196408662587, 8.4, null, 5080.09], "city__seeAlso__populationDensityKm": [8.4, 5080.09], "city__seeAlso__captionAlign": ["center"], "city__seeAlso__areaRank": [null], "city__seeAlso__populationTotal": [147182123, 13010112], "city__seeAlso__utcOffset": ["+2 to +12", "+3"], "city__seeAlso__nativeName": ["", "\u041f\u0440\u0430\u0432\u0438\u0442\u0435\u043b\u044c\u0441\u0442\u0432\u043e \u041c\u043e\u0441\u043a\u0432\u044b", "\u0414\u043e\u043c \u041f\u0440\u0430\u0432\u0438\u0442\u0435\u043b\u044c\u0441\u0442\u0432\u0430 \u0420\u043e\u0441\u0441\u0438\u0439\u0441\u043a\u043e\u0439 \u0424\u0435\u0434\u0435\u0440\u0430\u0446\u0438\u0438", "\u041c\u043e\u0441\u043a\u0432\u0430"], "city__seeAlso__populationDensitySqMi": [21.5], "city__seeAlso__percentageOfAreaWater": [13], "city__seeAlso__area": [null, 17098246000000], "city__seeAlso__license": ["CC BY 4.0"], "city__seeAlso__governmentType": ["Federal semi-presidential republic under an authoritarian dictatorship", "Federalism"], "city__seeAlso__demonym": ["Russian", "Muscovite"], "city__seeAlso__populationDensityRank": [null], "city__seeAlso__imageStyle": ["border:none;"], "city__seeAlso__ethnicGroup": ["Chechens", "Tatars", "Russians", "Bashkirs", "Chuvash_people", "Ukrainians_in_Russia", "Ethnic_groups_in_Russia"], "city__seeAlso__countryCode": ["+7"], "city__seeAlso__populationEstimateRank": [9], "city__seeAlso__sovereigntyType": ["History_of_Russia"], "city__seeAlso__giniChange": ["decrease"], "city__seeAlso__giniCoefficient": [36], "city__seeAlso__religionYear": [2012], "city__seeAlso__percentWater": [13], "city__seeAlso__gini": [36, 37.5], "city__seeAlso__giniYear": [2020], "city__seeAlso__language": ["Russian_language", "Languages_of_Russia"], "city__seeAlso__mapCaption": ["Russia on the globe, with claimed territory shown in light green."], "city__seeAlso__publisher": ["the International Energy Agency"], "city__seeAlso__author": ["International_Energy_Agency"], "city__seeAlso__commonName": ["Russia"], "city__seeAlso__conventionalLongName": ["Russian Federation"], "city__seeAlso__capital": ["Moscow"], "city__seeAlso__event": ["Russia__HistoricalEvent__8", "Russia__HistoricalEvent__9", "Russia__HistoricalEvent__6", "Russia__HistoricalEvent__7", "Russia__HistoricalEvent__4", "Russia__HistoricalEvent__5", "Russia__HistoricalEvent__2", "Russia__HistoricalEvent__3", "Russia__HistoricalEvent__10", "Russia__HistoricalEvent__11", "Russia__HistoricalEvent__1"], "city__seeAlso__documenturl": ["frequently-asked-questions-on-energy-security"], "city__seeAlso__licenseStatementUrl": ["ListordescriptionofCC-licensedContent_20220406.pdf"], "city__seeAlso__currency": ["Russian_ruble", "Russian ruble"], "city__seeAlso__areaFootnote": [null], "city__seeAlso__giniRank": [98], "city__seeAlso__languages2Type": ["", "national languages"], "city__seeAlso__currencyCode": ["RUB"], "city__seeAlso__gdpPppRank": [6], "city__seeAlso__gdpNominalRank": [9], "city__seeAlso__gdpPppPerCapitaRank": [59], "city__seeAlso__gdpNominalPerCapitaRank": [65], "city__seeAlso__ethnicGroupsYear": [2010], "city__seeAlso__cs1Dates": ["l"], "city__seeAlso__nationalAnthem": ["\"State Anthem of the Russian Federation\""], "city__seeAlso__direction": ["vertical", "horizontal"], "city__seeAlso__populationTotalRanking": [9, 1], "city__seeAlso__reason": ["Cited source doesn\u2019t mention drought, mentions role of weather as not directly affecting worst mortality surge", "Cited source doesn\u2019t mention transitional disorganization"], "city__seeAlso__languages": ["Russian_language", "See Languages of Russia"], "city__seeAlso__ethnicGroups": [80.9, 3.9, 1.1, 10.7, 1.4, ""], "city__seeAlso__mapWidth": [250], "city__seeAlso__cctld": [".ru", ".\u0440\u0444", ""], "city__seeAlso__establishedEvent": ["Grand_Duchy_of_Moscow", "Tsardom_of_Russia", "February_Revolution", "Russian_Empire", "Belovezha_Accords", "Soviet_Union", "Kievan_Rus'", "Declaration_of_State_Sovereignty_of_the_Russian_Soviet_Federative_Socialist_Republic", "Union_State", "Vladimir-Suzdal", "Constitution_of_Russia", ""], "city__seeAlso__gdpNominal": [null], "city__seeAlso__gdpNominalPerCapita": [null], "city__seeAlso__gdpNominalYear": [2022], "city__seeAlso__gdpPpp": [null], "city__seeAlso__gdpPppPerCapita": [null], "city__seeAlso__gdpPppYear": [2022], "city__seeAlso__hdi": [0.824, "", 0.743], "city__seeAlso__hdiYear": [2019], "city__seeAlso__languagesType": ["Official"], "city__seeAlso__linkingName": ["Russia"], "city__seeAlso__populationEstimate": [144699673, 147182123, ""], "city__seeAlso__populationEstimateYear": [2022], "city__seeAlso__topLevelDomain": [".ru", ".\u0440\u0444"], "city__seeAlso__humanDevelopmentIndex": [0.8240000009536743], "city__seeAlso__imageCoat": ["Coat of Arms of the Russian Federation.svg"], "city__seeAlso__closeMatch": ["13255-2", "18501-2"], "city__seeAlso__headerAlign": ["left/right/center"], "city__seeAlso__footerAlign": ["left/right/center", "center"], "city__homepage": ["", "en"], "city__exactMatch": ["i84008", "i84732", "i83991"], "city__lat": [59.9375, 55.75583267211914], "city__long": [30.3086109161377, 37.61722183227539], "city__subject": ["Category:Former_national_capitals", "Category:Port_cities_and_towns_of_the_Baltic_Sea", "Category:Port_cities_and_towns_in_Russia", "Category:1703_establishments_in_Europe", "Category:Populated_coastal_places_in_Russia", "Category:Federal_cities_of_Russia", "Category:1703_establishments_in_Russia", "Category:World_Heritage_Sites_in_Russia", "Category:Saint_Petersburg", "Category:Populated_places_established_in_1703", "Category:Sankt-Peterburgsky_Uyezd", "Category:Planned_capitals", "Category:Capitals_in_Europe", "Category:Populated_places_established_in_the_12th_century", "Category:Moskovsky_Uyezd", "Category:12th-century_establishments_in_Russia", "Category:Moscow"], "city__subject__broader": ["Category:Former_places", "Category:Historical_geography", "Category:Histories_of_capitals", "Category:Capitals_by_country", "Category:Baltic_Sea", "Category:Port_cities_in_Europe", "Category:Ports_and_harbours_of_the_Baltic_Sea", "Category:Port_cities_and_towns_of_the_Atlantic_Ocean", "Category:Port_cities_and_towns_by_sea_or_ocean", "Category:Port_cities_in_Asia", "Category:Port_cities_and_towns_by_country", "Category:Ports_and_harbours_of_Russia", "Category:Cities_and_towns_in_Russia", "Category:Populated_coastal_places_by_country", "Category:Populated_waterside_places_in_Russia", "Category:Coasts_of_Russia", "Category:Federal_subjects_of_Russia", "Category:1703_establishments_in_Europe", "Category:1703_establishments_in_Asia", "Category:World_Heritage_Sites_in_Europe_by_country", "Category:World_Heritage_Sites_by_country", "Category:Protected_areas_of_Russia", "Category:World_Heritage_Sites_in_Asia_by_country", "Category:Buildings_and_structures_in_Russia", "Category:Nature_conservation_in_Russia", "Category:Historic_sites_in_Russia", "Category:Tourist_attractions_in_Russia", "Category:Federal_cities_of_Russia", "Category:Wikipedia_categories_named_after_populated_places_in_Russia", "Category:Northwestern_Federal_District", "Category:Uezds_of_Saint_Petersburg_Governorate", "Category:Planned_cities", "Category:Moving_and_relocation", "Category:Capitals", "Category:Capitals_by_continent", "Category:Cities_in_Europe", "Category:Uezds_of_Moscow_Governorate", "Category:12th-century_establishments_in_Europe", "Category:12th-century_establishments_in_Asia", "Category:Capitals_in_Europe", "Category:Wikipedia_categories_named_after_capitals", "Category:Central_Federal_District"], "city__subject__related": ["Category:Capitals_of_former_nations"], "city__website": ["", "en"], "city__id": [540], "city__title": ["Religion in Saint Petersburg as of 2012", "Articles related to Saint Petersburg", "Religion in Moscow"], "city__caption": ["Catherine Palace in Tsarskoe Selo", "Population of Moscow by year"], "city__point": ["59.9375 30.308611111111112", "55.755833333333335 37.617222222222225"], "city__hypernym": ["City", "Capital"], "city__hypernym__seeAlso": ["Public_transport"], "city__hypernym__subject": ["Category:Urban_geography", "Category:Types_of_populated_places", "Category:Populated_places_by_type", "Category:Cities", "Category:City", "Category:Capital_(economics)"], "city__hypernym__hypernym": ["Settlement"], "city__hypernym__closeMatch": ["11966-0"], "city__hypernym__isPartOf": ["target"], "city__hypernym__s": ["Cities"], "city__hypernym__totalWidth": [350], "city__hypernym__footer": ["Left to right, from top: Westminster Palace in London, Shibuya Crossing in Tokyo, painting of Boulevard Montmartre in Paris by Camille Pissarro, the Rocinha favela in Rio de Janeiro, 6th Avenue in Manhattan, Taj Hotel in Mumbai, Hong Kong, the S\u00e3o Paulo Metro"], "city__hypernym__perrow": [1], "city__hypernym__alt": [null, "Skyscrapers line a busy sidewalk along 6th Avenue in New York City", "Crowd in front of Taj Hotel in Mumbai", "An underground train in the S\u00e3o Paulo Metro", "London skyline with Palace of Westminster in midground", "People cross busy Shibuya intersection lined with electronic billboards at dusk", "Hong Kong skyline", "Informal settlements built into the hillside in Rocinha, Rio de Janeiro, Brazil at dusk"], "city__hypernym__date": ["May 2022"], "city__hypernym__commons": ["Category:Cities"], "city__hypernym__wikt": ["city"], "city__hypernym__reason": ["Unusual wording - is it supposed to be \"any stake\" perhaps?"], "city__foundingDate": [1703], "city__imageCaption": ["Top-down, left-to-right: The Winter Palace; Palace Bridge; Peter and Paul Cathedral; Saint Isaac's Cathedral; the General Staff Building; the Moyka River from the Pevchesky Bridge to the Red Bridge"], "city__criteria": [", , ,"], "city__imageCoa": ["Coat of Arms of Saint Petersburg .svg"], "city__coaCaption": ["Coat_of_Arms_of_Saint_Petersburg"], "city__coaCaption__wikiPageRedirects": ["Coat_of_arms_of_Saint_Petersburg"], "city__areaKm2Rank": [82], "city__politicalStatus": ["Federal city"], "city__licensePlates": [7898178198], "city__economicRegion": ["Northwestern_economic_region"], "city__economicRegion__wikiPageRedirects": ["Northwestern_Economic_Region"], "city__flagCaption": ["Flag_of_Saint_Petersburg"], "city__flagCaption__subject": ["Category:Saint_Petersburg", "Category:Flags_introduced_in_1991", "Category:Flags_of_cities_in_Russia"], "city__flagCaption__adoption": [1991], "city__flagCaption__proportion": [2], "city__flagCaption__hypernym": ["Field"], "city__flagCaption__date": ["September 2014"], "city__flagCaption__otherarticle": ["\u0424\u043b\u0430\u0433 \u041c\u043e\u0441\u043a\u0432\u044b"], "city__politicalStatusLink": ["Federal cities of Russia"], "city__federalDistrict": ["Northwestern_Federal_District"], "city__federalDistrict__lat": [59.95000076293945], "city__federalDistrict__long": [30.3166675567627], "city__federalDistrict__subject": ["Category:Federal_districts_of_Russia", "Category:Northwestern_Federal_District", "Category:2000_establishments_in_Russia", "Category:States_and_territories_established_in_2000"], "city__federalDistrict__point": ["59.95 30.316666666666666"], "city__federalDistrict__hypernym": ["Districts"], "city__federalDistrict__foundingDate": [2000], "city__federalDistrict__nativeNameLang": ["ru"], "city__federalDistrict__populationDensityKm": ["auto"], "city__federalDistrict__originalName": ["\u0421\u0435\u0432\u0435\u0440\u043e-\u0417\u0430\u043f\u0430\u0434\u043d\u044b\u0439 \u0444\u0435\u0434\u0435\u0440\u0430\u043b\u044c\u043d\u044b\u0439 \u043e\u043a\u0440\u0443\u0433"], "city__federalDistrict__establishedTitle": ["Established"], "city__federalDistrict__establishedDate": [2000], "city__federalDistrict__seat": ["Saint_Petersburg"], "city__federalDistrict__seatType": ["Administrative centre"], "city__federalDistrict__areaRank": [4], "city__federalDistrict__geometry": [null], "city__federalDistrict__subdivisionType": ["Country"], "city__federalDistrict__populationAsOf": [2010], "city__federalDistrict__populationTotal": [13616057], "city__federalDistrict__settlementType": ["Federal district of Russia"], "city__federalDistrict__country": ["Russia"], "city__federalDistrict__unitPref": ["Metric"], "city__federalDistrict__nativeName": ["\u0421\u0435\u0432\u0435\u0440\u043e-\u0417\u0430\u043f\u0430\u0434\u043d\u044b\u0439 \u0444\u0435\u0434\u0435\u0440\u0430\u043b\u044c\u043d\u044b\u0439 \u043e\u043a\u0440\u0443\u0433"], "city__federalDistrict__blank1InfoSec": [3], "city__federalDistrict__blank1NameSec": ["Economic regions"], "city__federalDistrict__leaderTitle": ["Presidential Envoy"], "city__federalDistrict__mapCaption": ["Location of the Northwestern Federal District"], "city__federalDistrict__areaTotal": [null, 1687000000000], "city__federalDistrict__imageMap": ["Map of Russia - Northwestern Federal District .svg"], "city__federalDistrict__areaTotalKm": [1687000], "city__federalDistrict__politicalLeader": ["Northwestern_Federal_District__PoliticalFunction__1"], "city__federalDistrict__leaderName": ["Aleksandr_Gutsan"], "city__federalDistrict__blankInfoSec": [0.835, "\u00b7 3rd"], "city__federalDistrict__blankNameSec": ["Human_Development_Index", "Federal subjects"], "city__federalDistrict__populationTotalRanking": [5], "city__federalDistrict__populationRank": [5], "city__federalDistrict__totalType": ["Total"], "city__enName": ["Saint Petersburg"], "city__ruName": ["\u0421\u0430\u043d\u043a\u0442-\u041f\u0435\u0442\u0435\u0440\u0431\u0443\u0440\u0433"], "city__height": [397, 400, 422, 508, 175], "city__url": ["%3Flang=en", "moscow-housing-map"], "city__establishedTitle": ["Founded", "First mentioned"], "city__establishedDate": [1703, 1147], "city__r": ["Sankt-Peterburg", "Moskva"], "city__totalWidth": [350, 400], "city__anthem": ["Anthem_of_Saint_Petersburg", "File:\u0413\u0438\u043c\u043d_\u0421\u0430\u043d\u043a\u0442-\u041f\u0435\u0442\u0435\u0440\u0431\u0443\u0440\u0433\u0430.ogg", "Moya_Moskva", "\"My Moscow\""], "city__anthem__subject": ["Category:Saint_Petersburg", "Category:2003_songs", "Category:Russian_songs", "Category:Russian-language_songs", "Category:Russian_anthems", "Category:1941_songs", "Category:Soviet_songs", "Category:Culture_in_Moscow", "Category:20th_century_in_Moscow", "Category:Songs_about_Moscow", "Category:Compositions_by_Isaak_Dunayevsky"], "city__anthem__title": ["\u0413\u0438\u043c\u043d \u0421\u0430\u043d\u043a\u0442-\u041f\u0435\u0442\u0435\u0440\u0431\u0443\u0440\u0433\u0430", "\u041c\u043e\u044f \u041c\u043e\u0441\u043a\u0432\u0430"], "city__anthem__caption": ["Sheet notes"], "city__anthem__englishTitle": ["Anthem of Saint Petersburg", "'My Moscow'"], "city__anthem__musicDate": [1949], "city__anthem__lyricsDate": [2002], "city__anthem__adopted": [2003, 1995], "city__anthem__soundTitle": ["Anthem of Saint Petersbourg", "My Moscow instrumental version"], "city__anthem__transcription": ["Gimn Sankt-Peterburga", "Moja Moskva"], "city__anthem__composer": ["Reinhold_Gli\u00e8re", "Isaak_Dunayevsky"], "city__anthem__sound": ["\u0413\u0438\u043c\u043d \u0421\u0430\u043d\u043a\u0442-\u041f\u0435\u0442\u0435\u0440\u0431\u0443\u0440\u0433\u0430.ogg", "My Moscow.ogg"], "city__anthem__author": ["Oleg_Chuprov", "Mark Lisyansky", "Sergey Agranyan"], "city__p": ["\u02c8sankt p\u02b2\u026at\u02b2\u026ar\u02c8burk", "m\u0250sk\u02c8va"], "city__float": ["left"], "city__footer": ["Clockwise from left: Kronstadt: the Naval Cathedral on Yakornaya Square; the Church of St. Catherine; the Saint Petersburg Mosque; and the Grand Choral Synagogue of St. Petersburg", "The Bolshoi Theatre", "Clockwise from left: The Cathedral of Christ the Saviour, demolished during the Soviet period and reconstructed from 1990\u20132000; Cathedral of the Immaculate Conception; Moscow Cathedral Mosque; and Moscow Choral Synagogue"], "city__perrow": [2], "city__imageUpright": [1.2], "city__extension": [2013], "city__geometry": [null], "city__officialName": ["Historic Centre of Saint Petersburg and Related Groups of Monuments"], "city__country": ["Russia"], "city__country__seeAlso": ["Proto-Indo-Europeans", "Russia", "Timeline_of_Russian_innovation", "Russian_cuisine", "Moscow", "Third_Rome", "List_of_ecoregions"], "city__country__homepage": ["index_en.html"], "city__country__exactMatch": ["i83988", "i84002", "17534-6"], "city__country__lat": [55.75583267211914], "city__country__long": [37.61722183227539], "city__country__subject": ["Category:Member_states_of_the_United_Nations", "Category:Christian_states", "Category:Russia", "Category:E7_nations", "Category:Russian-speaking_countries_and_territories", "Category:1991_establishments_in_Europe", "Category:North_Asian_countries", "Category:Countries_in_Europe", "Category:Observer_states_of_the_Organisation_of_Islamic_Cooperation", "Category:Eastern_European_countries", "Category:BRICS_nations", "Category:Federal_republics", "Category:Member_states_of_the_Shanghai_Cooperation_Organisation", "Category:Transcontinental_countries", "Category:1991_establishments_in_Asia", "Category:Countries_in_Asia", "Category:Member_states_of_the_Commonwealth_of_Independent_States", "Category:States_and_territories_established_in_1991", "Category:G20_nations", "Category:Northeast_Asian_countries"], "city__country__title": ["Ethnic groups across Russia", "Minority languages across Russia", "Articles related to Russia", "Frequently Asked Questions on Energy Security"], "city__country__caption": ["Vladimir_Putin", "Mikhail_Mishustin", "(Prime Minister)", "Altaic and Uralic languages spoken across Russia", "(President)", "The North Caucasus is ethno-linguistically diverse."], "city__country__point": ["55.755833333333335 37.617222222222225"], "city__country__hypernym": ["State"], "city__country__upperHouse": ["Federation_Council_(Russia)"], "city__country__lowerHouse": ["State_Duma"], "city__country__hdiChange": ["increase"], "city__country__largestCity": ["capital"], "city__country__drivesOn": ["right"], "city__country__callingCode": ["Telephone_numbers_in_Russia"], "city__country__hdiRank": [52], "city__country__isPartOf": ["target"], "city__country__populationDensity": [8.301196408662587, 8.4, null], "city__country__populationDensityKm": [8.4], "city__country__establishedDate": [879, 1157, 1263, 1991, 1990, 1917, 1993, 1721, 1999, 1922, 1547], "city__country__totalWidth": [230, 300, 350], "city__country__anthem": ["State_Anthem_of_the_Russian_Federation"], "city__country__captionAlign": ["center"], "city__country__areaRank": [null], "city__country__perrow": [2], "city__country__geometry": [null], "city__country__populationTotal": [147182123], "city__country__utcOffset": ["+2 to +12"], "city__country__nativeName": [""], "city__country__populationDensitySqMi": [21.5], "city__country__percentageOfAreaWater": [13], "city__country__imageFlag": ["Flag of Russia.svg"], "city__country__area": [null, 17098246000000], "city__country__areaKm": [17098246], "city__country__license": ["CC BY 4.0"], "city__country__governmentType": ["Federal semi-presidential republic under an authoritarian dictatorship", "Federalism"], "city__country__demonym": ["Russian"], "city__country__populationDensityRank": [null], "city__country__imageStyle": ["border:none;"], "city__country__ethnicGroup": ["Chechens", "Tatars", "Russians", "Bashkirs", "Chuvash_people", "Ukrainians_in_Russia", "Ethnic_groups_in_Russia"], "city__country__countryCode": ["+7"], "city__country__populationEstimateRank": [9], "city__country__sovereigntyType": ["History_of_Russia"], "city__country__giniChange": ["decrease"], "city__country__giniCoefficient": [36], "city__country__religionYear": [2012], "city__country__percentWater": [13], "city__country__gini": [36], "city__country__giniYear": [2020], "city__country__language": ["Russian_language", "Languages_of_Russia"], "city__country__leaderTitle": ["Chairman_of_the_Federation_Council_(Russia)", "Chairman_of_the_State_Duma", "Chief_Justice_of_the_Russian_Federation", "Prime_Minister_of_Russia", "President_of_Russia"], "city__country__mapCaption": ["Russia on the globe, with claimed territory shown in light green."], "city__country__imageMap": ["Russian Federation  - Annexed Territories disputed.svg"], "city__country__leaderName": ["Vladimir_Putin", "Vyacheslav_Volodin", "Vyacheslav_Mikhailovich_Lebedev", "Mikhail_Mishustin", "Valentina_Matviyenko"], "city__country__publisher": ["the International Energy Agency"], "city__country__date": ["June 2022", "November 2022"], "city__country__align": ["left", "right"], "city__country__author": ["International_Energy_Agency"], "city__country__commonName": ["Russia"], "city__country__conventionalLongName": ["Russian Federation"], "city__country__capital": ["Moscow"], "city__country__event": ["Russia__HistoricalEvent__8", "Russia__HistoricalEvent__9", "Russia__HistoricalEvent__6", "Russia__HistoricalEvent__7", "Russia__HistoricalEvent__4", "Russia__HistoricalEvent__5", "Russia__HistoricalEvent__2", "Russia__HistoricalEvent__3", "Russia__HistoricalEvent__10", "Russia__HistoricalEvent__11", "Russia__HistoricalEvent__1"], "city__country__documenturl": ["frequently-asked-questions-on-energy-security"], "city__country__licenseStatementUrl": ["ListordescriptionofCC-licensedContent_20220406.pdf"], "city__country__currency": ["Russian_ruble", "Russian ruble"], "city__country__areaFootnote": [null], "city__country__giniRank": [98], "city__country__languages2Type": ["", "national languages"], "city__country__currencyCode": ["RUB"], "city__country__gdpPppRank": [6], "city__country__gdpNominalRank": [9], "city__country__gdpPppPerCapitaRank": [59], "city__country__gdpNominalPerCapitaRank": [65], "city__country__ethnicGroupsYear": [2010], "city__country__cs1Dates": ["l"], "city__country__nationalAnthem": ["\"State Anthem of the Russian Federation\""], "city__country__direction": ["vertical"], "city__country__populationTotalRanking": [9], "city__country__reason": ["Cited source doesn\u2019t mention drought, mentions role of weather as not directly affecting worst mortality surge", "Cited source doesn\u2019t mention transitional disorganization"], "city__country__languages": ["Russian_language", "See Languages of Russia"], "city__country__ethnicGroups": [80.9, 3.9, 1.1, 10.7, 1.4, ""], "city__country__legislature": ["Federal_Assembly_(Russia)"], "city__country__mapWidth": [250], "city__country__cctld": [".ru", ".\u0440\u0444", ""], "city__country__establishedEvent": ["Grand_Duchy_of_Moscow", "Tsardom_of_Russia", "February_Revolution", "Russian_Empire", "Belovezha_Accords", "Soviet_Union", "Kievan_Rus'", "Declaration_of_State_Sovereignty_of_the_Russian_Soviet_Federative_Socialist_Republic", "Union_State", "Vladimir-Suzdal", "Constitution_of_Russia", ""], "city__country__gdpNominal": [null], "city__country__gdpNominalPerCapita": [null], "city__country__gdpNominalYear": [2022], "city__country__gdpPpp": [null], "city__country__gdpPppPerCapita": [null], "city__country__gdpPppYear": [2022], "city__country__hdi": [0.824], "city__country__hdiYear": [2019], "city__country__languagesType": ["Official"], "city__country__linkingName": ["Russia"], "city__country__populationEstimate": [144699673, 147182123, ""], "city__country__populationEstimateYear": [2022], "city__country__topLevelDomain": [".ru", ".\u0440\u0444"], "city__country__humanDevelopmentIndex": [0.8240000009536743], "city__country__imageCoat": ["Coat of Arms of the Russian Federation.svg"], "city__imageFlag": ["Flag of Saint Petersburg Russia.svg", "Flag of Moscow, Russia.svg"], "city__year": [1990], "city__areaKm": [1439], "city__leaderTitle": ["Governor", "Governor_of_Saint_Petersburg", "Mayor_of_Moscow"], "city__leaderTitle__homepage": [""], "city__leaderTitle__subject": ["Category:Governors_of_Saint_Petersburg", "Category:Lists_of_heads_of_the_federal_subjects_of_Russia", "Category:Government_of_Saint_Petersburg", "Category:Lists_of_mayors_of_places_in_Russia", "Category:1991_establishments_in_Russia", "Category:Mayors_of_Moscow", "Category:Government_of_Moscow"], "city__leaderTitle__website": [""], "city__leaderTitle__hypernym": ["Head"], "city__leaderTitle__status": ["Head of the Executive branch of Saint Petersburg"], "city__leaderTitle__insigniacaption": ["Flag_of_Saint_Petersburg", "Flag_of_Moscow"], "city__leaderTitle__residence": ["Saint_Petersburg", "Smolny_Institute", 13], "city__leaderTitle__body": ["the City of Saint Petersburg", "Moscow"], "city__leaderTitle__formation": [1703, 1991], "city__leaderTitle__seat": ["Smolny_Institute", "Moscow_City_House"], "city__leaderTitle__nativeName": ["\u0413\u0443\u0431\u0435\u0440\u043d\u0430\u0442\u043e\u0440 \u0421\u0430\u043d\u043a\u0442-\u041f\u0435\u0442\u0435\u0440\u0431\u0443\u0440\u0433\u0430"], "city__leaderTitle__imagesize": [165], "city__leaderTitle__salary": [9700000], "city__leaderTitle__nominater": ["President_of_Russia"], "city__leaderTitle__post": ["Governor_(Russia)", "Mayor"], "city__leaderTitle__style": ["His Excellency, Mr. Governor", "His Excellency\nMr. Mayor"], "city__leaderTitle__appointer": ["Popular votes", "Popular vote"], "city__leaderTitle__constitutingInstrument": ["Charter_of_Saint_Petersburg"], "city__leaderTitle__incumbent": ["Alexander_Beglov", "Sergey_Sobyanin"], "city__leaderTitle__termlength": [null], "city__leaderTitle__incumbentsince": [2019, 2010], "city__leaderTitle__inaugural": ["Alexander_Danilovich_Menshikov", "Gavriil_Kharitonovich_Popov"], "city__leaderTitle__insignia": ["Flag of Saint Petersburg Russia.svg", "Flag of Moscow, Russia.svg"], "city__leaderTitle__insigniasize": [150], "city__leaderTitle__precursor": ["Governor-General of Saint Petersburg Province"], "city__leaderTitle__succession": ["Deputy Governor"], "city__areaTotal": [null, 1439000000, 2561498241.122304, 2561500000], "city__imageMap": ["Russia Saint Petersburg locator map.svg", "Russia Moscow locator map.svg"], "city__leaderName": ["Alexander Beglov", "Alexander_Beglov", "Sergey_Sobyanin"], "city__date": ["October 2018", "November 2021", 2014, 2020, "January 2021", "January 2011"], "city__align": ["right", "left"], "city__width": [500, 560, 595, 530, 1250, 2230], "city__links": ["no"], "city__leaderName__homepage": ["%7CInstagram", "sobyanin.ru", ""], "city__leaderName__subject": ["Category:Living_people", "Category:Recipients_of_the_Order_%22For_Merit_to_the_Fatherland%22,_4th_class", "Category:Governors_of_Saint_Petersburg", "Category:Saint-Petersburg_State_University_of_Architecture_and_Civil_Engineering_alumni", "Category:Russian_politicians", "Category:Politicians_from_Baku", "Category:1956_births", "Category:Russian_individuals_subject_to_the_U.S._Department_of_the_Treasury_sanctions", "Category:1st_class_Active_State_Councillors_of_the_Russian_Federation", "Category:Engineers_from_Baku", "Category:Kutafin_Moscow_State_Law_University_alumni", "Category:Soviet_politicians", "Category:Governors_of_Tyumen_Oblast", "Category:Specially_Designated_Nationals_and_Blocked_Persons_List", "Category:Sergey_Sobyanin", "Category:Mansi_people", "Category:Russian_nationalists", "Category:People_from_Beryozovsky_District,_Khanty-Mansi_Autonomous_Okrug", "Category:Mayors_of_Moscow", "Category:1958_births", "Category:Anti-Ukrainian_sentiment_in_Russia", "Category:21st-century_Russian_politicians", "Category:United_Russia_politicians", "Category:Russian_engineers", "Category:Kremlin_Chiefs_of_Staff", "Category:Komsomol"], "city__leaderName__website": ["%7CInstagram"], "city__leaderName__title": ["Governor_of_Saint_Petersburg", "Governor of Saint Petersburg", "Mayor_of_Moscow", "Chief of the Russian presidential administration", "Sergey Sobyanin's voice"], "city__leaderName__hypernym": ["Statesman"], "city__leaderName__termStart": [2003, 2017, 2018, 2012, 2001, 2010, 2008, 2005], "city__leaderName__office": [3, "Governor_of_Saint_Petersburg", "Acting Governor of Saint Petersburg", "Presidential Envoy of the Northwestern Federal District", "Deputy_Chairman_of_the_Government_of_the_Russian_Federation", "Kremlin_Chief_of_Staff", "Mayor_of_Moscow", "Governor_of_Tyumen_Oblast"], "city__leaderName__termEnd": [2017, 2003, 2018, 2010, 2008, 2005], "city__leaderName__termPeriod": ["Alexander_Beglov__Tenure__4", "Alexander_Beglov__Tenure__1", "Alexander_Beglov__Tenure__2", "Alexander_Beglov__Tenure__3", "Sergey_Sobyanin__Tenure__4", "Sergey_Sobyanin__Tenure__3", "Sergey_Sobyanin__Tenure__2", "Sergey_Sobyanin__Tenure__1"], "city__leaderName__party": ["United_Russia", "CPSU", "Communist_Party_of_the_Soviet_Union"], "city__leaderName__years": [2003, 2019, 2005, 2010], "city__leaderName__spouse": ["Natalia Beglova", 2014, "", "Irina Sobyanina", "divorced"], "city__leaderName__successor": ["Aleksandr_Gutsan", "Alexey_Gordeyev", "Valentina_Matviyenko", "Vladimir_Yakushev", "Sergey_Naryshkin", "Vyacheslav_Volodin"], "city__leaderName__predecessor": ["Georgy_Poltavchenko", "Vladimir_Anatolyevich_Yakovlev", "Nikolay_Tsukanov", "Oleg_Govorun", "Yury_Luzhkov", "Dmitry_Medvedev", "Vladimir_Resin", "Sergey_Naryshkin", "Leonid Roketsky"], "city__leaderName__children": [3], "city__iso": ["RU-SPE"], "city__a": ["Ru-Sankt Peterburg Leningrad Petrograd Piter.ogg", "\u041c\u043e\u0441\u043a\u0432\u0430.ogg"], "city__certain": ["y"], "city__legislature": ["Legislative_Assembly_of_Saint_Petersburg"], "city__legislature__homepage": [""], "city__legislature__subject": ["Category:Unicameral_legislatures", "Category:Legislatures_of_the_federal_subjects_of_Russia", "Category:1994_establishments_in_Russia", "Category:Government_of_Saint_Petersburg"], "city__legislature__website": [""], "city__legislature__hypernym": ["Body"], "city__legislature__lastElectionDate": [2021], "city__legislature__legislativePeriodName": ["", "7th legislature"], "city__legislature__coaRes": [110], "city__legislature__location": ["Saint_Petersburg", "Mariinsky_Palace"], "city__legislature__party": ["United_Russia"], "city__legislature__nextElection": [2026], "city__legislature__lastElection": [2021], "city__legislature__nativeName": ["\u0417\u0430\u043a\u043e\u043d\u043e\u0434\u0430\u0442\u0435\u043b\u044c\u043d\u043e\u0435 \u0441\u043e\u0431\u0440\u0430\u043d\u0438\u0435 \u0421\u0430\u043d\u043a\u0442-\u041f\u0435\u0442\u0435\u0440\u0431\u0443\u0440\u0433\u0430"], "city__legislature__leader": ["Vyacheslav Makarov", "Vyacheslav_Makarov"], "city__legislature__meetingPlace": [250, "Saint Petersburg, St. Isaac Square 6, Mariinsky Palace", "Legislative Assembly Building"], "city__legislature__votingSystem": ["Mixed_electoral_system"], "city__legislature__structure1Res": [250], "city__legislature__election": [2011], "city__legislature__structure": ["File:2021_Saint_Petersburg_legislative_election_diagram.svg"], "city__legislature__members": [50], "city__legislature__houseType": ["Unicameralism"], "city__legislature__electionDateLeader": [2011], "city__legislature__politicalGroups": ["Yabloko", "United Russia", "CPRF", "LDPR", "SRZP", "New People"], "city__legislature__politicalPartyInLegislature": ["Communist_Party_of_the_Russian_Federation", "Yabloko", "Liberal_Democratic_Party_of_Russia", "A_Just_Russia", "United_Russia", "New_People_(political_party)"], "city__legislature__politicalPartyOfLeader": ["United_Russia"], "city__legislature__leader1Type": ["Chairman"], "city__legislature__numberOfMembers": [50], "city__legislature__coaPic": ["Coat of Arms of Saint Petersburg .svg"], "city__legislature__legislature": [7], "city__differentFrom": ["Moscow_Oblast"], "city__differentFrom__seeAlso": ["Grand_Duchy_of_Moscow"], "city__differentFrom__lat": [55.70000076293945], "city__differentFrom__long": [36.96666717529297], "city__differentFrom__subject": ["Category:Moscow_Oblast", "Category:States_and_territories_established_in_1929", "Category:1929_establishments_in_Russia"], "city__differentFrom__location": ["Moscow Oblast"], "city__differentFrom__title": ["Religion in Moscow Oblast as of 2012"], "city__differentFrom__point": ["55.7 36.96666666666667"], "city__differentFrom__hypernym": ["Subject"], "city__differentFrom__imageCoa": ["Coat of arms of Moscow Oblast .svg"], "city__differentFrom__govAsOf": ["February 2015"], "city__differentFrom__popLatestDate": ["January 2015"], "city__differentFrom__coaCaption": ["Coat of arms"], "city__differentFrom__admCtrType": ["Administrative_center"], "city__differentFrom__areaKm2Rank": [55], "city__differentFrom__politicalStatus": ["Oblast"], "city__differentFrom__popLatest": [7231068], "city__differentFrom__urbanPop2010census": [null], "city__differentFrom__licensePlates": [5090150190750790], "city__differentFrom__ruralPop2010census": [null], "city__differentFrom__economicRegion": ["Central_economic_region"], "city__differentFrom__flagCaption": ["Flag"], "city__differentFrom__pop2010censusRank": [2], "city__differentFrom__admCtrName": ["none"], "city__differentFrom__politicalStatusLink": ["Oblasts of Russia"], "city__differentFrom__federalDistrict": ["Central_Federal_District"], "city__differentFrom__pop2010census": [7095120], "city__differentFrom__enName": ["Moscow Oblast"], "city__differentFrom__ruName": ["\u041c\u043e\u0441\u043a\u043e\u0432\u0441\u043a\u0430\u044f \u043e\u0431\u043b\u0430\u0441\u0442\u044c"], "city__differentFrom__establishedDate": ["January 14, 1929"], "city__differentFrom__float": ["right"], "city__differentFrom__geometry": [null], "city__differentFrom__country": ["Russia"], "city__differentFrom__imageFlag": ["Flag of Moscow oblast.svg"], "city__differentFrom__areaKm": [44300], "city__differentFrom__yearHighC": [9.8], "city__differentFrom__yearLowC": [2.8], "city__differentFrom__yearMeanC": [6.3], "city__differentFrom__leaderTitle": ["Governor", "Governor_of_Moscow_Oblast"], "city__differentFrom__areaTotal": [null, 44300000000], "city__differentFrom__imageMap": ["Map of Russia - Moscow Oblast.svg"], "city__differentFrom__leaderName": ["Andrey_Yuryevich_Vorobyov"], "city__differentFrom__source": ["protown.ru"], "city__differentFrom__date": ["January 2016"], "city__differentFrom__width": ["auto"], "city__differentFrom__iso": ["RU-MOS"], "city__differentFrom__decLowC": [-11], "city__differentFrom__octLowC": [1], "city__differentFrom__janMeanC": [-10], "city__differentFrom__metricFirst": ["yes"], "city__differentFrom__julMeanC": [19], "city__differentFrom__mayHighC": [18], "city__differentFrom__febHighC": [-5], "city__differentFrom__octHighC": [8], "city__differentFrom__sepMeanC": [11], "city__differentFrom__augHighC": [23], "city__differentFrom__aprMeanC": [6], "city__differentFrom__marMeanC": [-4], "city__differentFrom__aprHighC": [11], "city__differentFrom__junHighC": [22], "city__differentFrom__decMeanC": [-7], "city__differentFrom__novLowC": [-6], "city__differentFrom__novHighC": [2], "city__differentFrom__octMeanC": [5], "city__differentFrom__sepHighC": [16], "city__differentFrom__febLowC": [-15], "city__differentFrom__mayMeanC": [13], "city__differentFrom__julLowC": [13], "city__differentFrom__augLowC": [11], "city__differentFrom__janLowC": [-14], "city__differentFrom__novMeanC": [-2], "city__differentFrom__junMeanC": [17], "city__differentFrom__decHighC": [-4], "city__differentFrom__singleLine": ["yes"], "city__differentFrom__julHighC": [25], "city__differentFrom__augMeanC": [17], "city__differentFrom__aprLowC": [1], "city__differentFrom__janHighC": [-6], "city__differentFrom__marHighC": [1], "city__differentFrom__marLowC": [-9], "city__differentFrom__sepLowC": [6], "city__differentFrom__febMeanC": [-10], "city__differentFrom__mayLowC": [8], "city__differentFrom__junLowC": [12], "city__differentFrom__legislature": ["Moscow_Oblast_Duma"], "city__seeAlso__differentFrom": ["List_of_tallest_structures", "List_of_tallest_freestanding_structures", "City_Hall", "City_Duma", "Mayor_of_Moscow", "Moscow_City_Duma", "Internet_Protocol_television", "Web_television", "Internet_television", "Smart_television", "Moscow_Oblast"], "city__seeAlso__label1Width": [10], "city__seeAlso__label3Width": [10], "city__seeAlso__label4Width": [12], "city__seeAlso__label6Width": [10], "city__seeAlso__label8Width": [10], "city__seeAlso__label9Width": [10], "city__seeAlso__group": ["note", "Developing_country", "", "Upper-middle income economy"], "city__seeAlso__pos": ["left", "bottom", "right", "top"], "city__seeAlso__link": ["China Zun", "Taipei 101", "Abraj Al Bait", "Ping An International Finance Centre", "Shanghai Tower", "One World Trade Center", "Burj Khalifa", "Merdeka 118", "Lotte World Tower", "Tianjin CTF Finance Centre", "Guangzhou CTF Finance Centre"], "city__seeAlso__dataType": ["fleet in units"], "city__seeAlso__data": [4.2, 13.9, 15.4, 16.5, 19.8], "city__seeAlso__dataMax": [20], "city__seeAlso__widthUnits": ["px"], "city__seeAlso__labelType": ["city"], "city__seeAlso__barWidth": [275], "city__seeAlso__nativeNameLang": ["ru"], "city__seeAlso__imageSkyline": ["Tverskaya13 Moscow 06-2015.jpg"], "city__seeAlso__flagSize": [75, 120], "city__seeAlso__shieldSize": [50, 75], "city__seeAlso__settlementType": ["Federal_cities_of_Russia", "Capital city and federal city"], "city__seeAlso__imageShield": ["Coat of Arms of Moscow.svg"], "city__seeAlso__blankInfoSec": [13], "city__seeAlso__blankNameSec": ["Administration center"], "city__seeAlso__text": ["\"The first shell hit the meeting room, the second in Khasbulatov's office, the third in mine. And they were beaten with high-explosive shells, not insacks, as they claim today. The building will not burn from the dummy. I was sitting in my office when the projectile broke the window and exploded in the right corner [of the room]. Fortunately, my table was on my left. A stunned man came out of there. I don't know what saved me.\""], "city__seeAlso__location": ["Moscow", "Moscow  normals 1961\u20131990"], "city__seeAlso__originalName": ["\u0414\u043e\u043c \u041f\u0440\u0430\u0432\u0438\u0442\u0435\u043b\u044c\u0441\u0442\u0432\u0430 \u0420\u043e\u0441\u0441\u0438\u0439\u0441\u043a\u043e\u0439 \u0424\u0435\u0434\u0435\u0440\u0430\u0446\u0438\u0438", "\u041c\u043e\u0441\u043a\u0432\u0430"], "city__seeAlso__mapType": ["Russia Moscow"], "city__seeAlso__formerName": ["House of Soviets of theRSFSR", "House of Soviets of theRussian Federation"], "city__seeAlso__imageSize": [250, 310], "city__seeAlso__locationCountry": ["Russia"], "city__seeAlso__architect": ["Dmitry_Chechulin", "Pavel_Shteller"], "city__seeAlso__locationTown": ["Moscow"], "city__seeAlso__buildingType": ["Parliament"], "city__seeAlso__style": ["Soviet modernism"], "city__seeAlso__formerNames": ["House of Soviets of the Russian Federation", "House of Soviets of the RSFSR"], "city__seeAlso__by": ["no"], "city__seeAlso__others": ["no"], "city__seeAlso__about": ["yes"], "city__seeAlso__onlinebooks": ["no"], "city__seeAlso__elevation": [156], "city__seeAlso__elevationM": [156], "city__seeAlso__video": ["watch%3Fv=bsLRYMM3ORs", "watch%3Fv=f9p20dxtTkY"], "city__seeAlso__blankInfo": [45000000], "city__seeAlso__blankName": ["OKTMO ID"], "city__seeAlso__governingBody": ["Moscow_City_Duma"], "city__seeAlso__isoCodeRegion": ["RU-MOW"], "city__seeAlso__isoCode": ["RU-MOW"], "city__seeAlso__content": ["Chart\n | width=400\n | height=200\n | type=area\n | colors=#99B2CC\n | xAxisMin=1350|xAxisMax=2018\n | xAxisTitle=Year\n | x= 1350, 1400, 1600, 1638, 1710, 1725, 1738, 1750, 1775, 1785, 1800, 1811, 1813, 1825, 1830, 1835, 1840, 1847, 1852, 1856, 1858, 1859, 1863, 1864, 1868, 1871, 1886, 1891, 1897, 1900, 1902, 1907, 1908, 1912, 1913, 1914, 1915, 1917, 1920, 1923, 1926, 1928, 1931, 1936, 1939, 1956, 1959, 1967, 1970, 1972, 1973, 1975, 1976, 1979, 1982, 1985, 1986, 1987, 1989, 1990, 1991, 1992, 1993, 1994, 1995, 1996, 1997, 1998, 1999, 2000, 2001, 2002, 2003, 2004, 2005, 2006, 2007, 2008, 2009, 2010, 2011, 2012, 2013, 2014, 2015, 2016, 2018\n | yAxisFormat=s | yGrid= \n | yAxisTitle=Population\n | y= 30000, 40000, 100000, 200000, 160000, 145000, 138400, 130000, 161000, 188700, 250000, 270200, 215000, 241500, 305600, 335800, 349100, 353300, 373800, 368800, 377800, 379300, 462500, 351600, 416400, 601969, 753459, 822400, 1039000, 1175000, 1174700, 1345700, 1359200, 1617157, 1563100, 1762700, 1817000, 1854400, 1028200, 1542900, 2080000, 2127200, 2781300, 3641500, 4131633, 4839000, 5045905, 6422000, 6941961, 7151000, 7255000, 7862000, 7658000, 7830509, 8111000, 8652000, 8527000, 8815000, 8769117, 8880124, 9017415, 9067808, 9066025, 9066612, 9085457, 9246727, 9411236, 9604297, 9783242, 9932932, 10114203, 10269900, 10386903, 10535681, 10726429, 10923762, 11091428, 11186851, 11281631, 11503501, 11776764, 11856578, 11979529, 12108257, 12197596, 12330126, 13010112"], "city__seeAlso__subdivisionType": ["Economic_regions_of_Russia", "Federal_districts_of_Russia", "Country"], "city__seeAlso__populationAsOf": [2021], "city__seeAlso__subdivisionName": ["Central_economic_region", "Central_Federal_District"], "city__seeAlso__subdivision": ["Central_economic_region", "Central_Federal_District"], "city__seeAlso__timeZone": ["Moscow_Time"], "city__seeAlso__timezone": ["Moscow_Time"], "city__seeAlso__areaTotalSqMi": [989], "city__seeAlso__alt": ["Panorama of Moscow in 1819-1823"], "city__seeAlso__yearHighC": [10.2, 8.9], "city__seeAlso__yearLowC": [1.2, 3.1], "city__seeAlso__yearMeanC": [5, 6.6], "city__seeAlso__registrationPlate": [77177777], "city__seeAlso__populationDemonym": ["Muscovite"], "city__seeAlso__areaTotalKm": [2561.5], "city__seeAlso__politicalLeader": ["Moscow__PoliticalFunction__1"], "city__seeAlso__source": ["weatheronline.co.uk"], "city__seeAlso__collapsed": ["yes"], "city__seeAlso__fullwidth": [12569], "city__seeAlso__fullheight": [600], "city__seeAlso__blank6Name": ["Gross_Regional_Product"], "city__seeAlso__blank6Info": ["\u20bd20 trillion"], "city__seeAlso__shieldLink": ["Coat of arms of Moscow"], "city__seeAlso__decLowC": ["\u22125.4", "\u22128.6"], "city__seeAlso__octLowC": [2, 3.1], "city__seeAlso__janMeanC": ["\u22127.9", "\u22129.3"], "city__seeAlso__metricFirst": ["Yes", "yes"], "city__seeAlso__julMeanC": [20.7, 18.2], "city__seeAlso__mayHighC": [18.4, 20.1], "city__seeAlso__febHighC": ["\u22123.6", "\u22124.2"], "city__seeAlso__octHighC": [8.2, 7.9], "city__seeAlso__sepMeanC": [12.9, 11.1], "city__seeAlso__augHighC": [21.5, 23.9], "city__seeAlso__aprMeanC": [6.9, 5.8], "city__seeAlso__marMeanC": ["\u22122.2", "\u22121.0"], "city__seeAlso__aprHighC": [10.4, 11.4], "city__seeAlso__augSun": [242], "city__seeAlso__junSun": [299], "city__seeAlso__janSun": [37], "city__seeAlso__junHighC": [21.7, 22.6], "city__seeAlso__decMeanC": ["\u22126.1", "\u22123.9"], "city__seeAlso__novLowC": ["\u22120.7", "\u22123.3"], "city__seeAlso__novHighC": [2.1, 1.1], "city__seeAlso__octMeanC": [5.5, 5.1], "city__seeAlso__sepHighC": [16.7, 15.4], "city__seeAlso__febLowC": ["\u221211.1", "\u22128.3"], "city__seeAlso__mayMeanC": [14.7, 13.1], "city__seeAlso__julLowC": [15.6, 13.5], "city__seeAlso__augLowC": [12, 13.8], "city__seeAlso__octSun": [88], "city__seeAlso__aprSun": [213], "city__seeAlso__julSun": [323], "city__seeAlso__novSun": [33], "city__seeAlso__janLowC": ["\u221212.3", "\u22129.7"], "city__seeAlso__sepSun": [171], "city__seeAlso__novMeanC": [0.7, "\u22121.2"], "city__seeAlso__junMeanC": [16.6, 17.6], "city__seeAlso__decHighC": ["\u22122.4", "\u22123.5"], "city__seeAlso__singleLine": ["Yes", "yes"], "city__seeAlso__julHighC": [23.1, 25.8], "city__seeAlso__augMeanC": [18.9, 16.4], "city__seeAlso__aprLowC": [2.3, 1.7], "city__seeAlso__janHighC": ["\u22126.3", "\u22126.0"], "city__seeAlso__populationMetro": [20004462], "city__seeAlso__marHighC": [1.5, 2.4], "city__seeAlso__mapsize": [295], "city__seeAlso__marLowC": ["\u22125.6", "\u22124.5"], "city__seeAlso__sepLowC": [7.1, 9.1], "city__seeAlso__febMeanC": ["\u22127.7", "\u22126.0"], "city__seeAlso__mayLowC": [9.4, 7.6], "city__seeAlso__junLowC": [11.5, 12.5], "city__seeAlso__decSun": [14], "city__seeAlso__populationRank": [null], "city__seeAlso__marSun": [142], "city__seeAlso__maySun": [274], "city__seeAlso__febSun": [65], "city__seeAlso__totalType": ["Total"], "city__seeAlso__flagLink": ["Flag of Moscow"], "city__seeAlso__growth": ["", "\u20133.4%  \u2013-2.3%", "\u20132.7%  4.7%"], "city__seeAlso__reserves": [null], "city__seeAlso__revenue": [258600000000], "city__seeAlso__population": [147182123], "city__seeAlso__abbr": ["su"], "city__seeAlso__gdpRank": [6, 9, ""], "city__seeAlso__expenses": [281400000000], "city__seeAlso__gdp": ["", null], "city__seeAlso__unemployment": ["", null], "city__seeAlso__averageGrossSalary": ["RUB 63,874 / \u20ac1,006 monthly"], "city__seeAlso__averageNetSalary": ["RUB 55,570 / \u20ac876 monthly"], "city__seeAlso__balance": [null], "city__seeAlso__debt": [10.6], "city__seeAlso__exports": [null], "city__seeAlso__fdi": ["Abroad: $470.9 billion", null], "city__seeAlso__grossExternalDebt": [null], "city__seeAlso__imports": [null], "city__seeAlso__inflation": [null], "city__seeAlso__perCapita": ["", null], "city__seeAlso__perCapitaRank": [55, 61, ""], "city__seeAlso__poverty": ["", 2.2, null], "city__seeAlso__spelling": ["US"], "city__seeAlso__sectors": ["", "services: 62.3%", "industry: 32.4%", "agriculture: 4.7%"], "city__seeAlso__importGoods": ["cars and vehicle parts, packaged medicines, broadcasting equipment, aircraft, computers"], "city__seeAlso__currentAccount": [null], "city__seeAlso__industries": ["Complete range of mining and extractive industries producing coal, oil, gas, chemicals, and metals; all forms of machine building from rolling mills to high-performance aircraft and space vehicles; defense industries , shipbuilding; road and rail transportation equipment; communications equipment; agricultural machinery, tractors, and construction equipment; electric power generating and transmitting equipment; medical and scientific instruments; consumer durables, textiles, foodstuffs, handicrafts"], "city__seeAlso__credit": ["Standard_&_Poor's", "Fitch_Group", "Moody's", "", "Outlook: Positive\n----", "BB+", "Outlook: Positive", "BBB-", "Outlook: Stable\n----", "Ba1"], "city__seeAlso__occupations": ["", "services: 63%", "industry: 27.6%", "agriculture: 9.4%"], "city__seeAlso__labor": [59.8, ""], "city__seeAlso__exportGoods": ["crude petroleum, refined petroleum, natural gas, coal, wheat, iron"], "city__seeAlso__organs": ["WTO, BRICS, EAEU, CIS, GECF, APEC, G-20 and others"], "city__seeAlso__cianame": ["russia"], "city__seeAlso__summary": ["Football codes"], "city__location": ["Moscow", "Moscow  normals 1961\u20131990"], "city__hypernym__differentFrom": ["Capitol_(disambiguation)"], "city__hypernym__wikiPageDisambiguates": ["Capital_(architecture)", "Economic_capital", "Capital_good", "Human_capital", "List_of_national_capitals", "Capital_(Ukrainian_newspaper)", "Financial_capital", "Category:Capital_(economics)", "Public_capital", "Capital_(British_TV_series)", "Capital_(album)", "Capital_New_York", "Capital_city", "A_Capital", "Capital_(Romanian_magazine)", "Capital_Community_College", "Capital_(film)", "Capital_University,_Jharkhand", "Capitals_(typeface)", "Capital_ship", "Capital_CF", "Capital_(Iranian_TV_series)", "Capital_University", "Capital_(French_magazine)", "The_Capital_(building)", "Social_capital", "Capital_(economics)", "Vienna_Capitals", "Capital_(Ethiopia)", "Capital_TV", "Delhi_Capitals", "Capital_(band)", "Edmonton_Capitals", "Capital_(German_magazine)", "Capital_Airlines_(disambiguation)", "Capital_(Marxism)", "Capital_TV_(Belarus)", "Capital_(sidewheeler)", "Capital_(radio_network)", "Capital_(novel)", "Washington_Capitals", "Natural_capital", "Capital:_The_Eruption_of_Delhi", "Capital_in_the_Twenty-First_Century", "Capital_region_(disambiguation)", "Capital_City_(disambiguation)", "Capital_College_(disambiguation)", "Capital_Radio_(disambiguation)", "Capitalism_(disambiguation)", "Capital_(fortification)", "Edinburgh_Capitals", "Capital_(newspaper)", "Instructional_capital", "Capital_letter", "University_of_Canberra_Capitals", "The_Capital", "Delhi_Capitals_(basketball)", "Capitalization_(disambiguation)"], "city__populationDensity": [5080.09, null], "city__elevation": [156], "city__populationDensityKm": [5080.09], "city__elevationM": [156], "city__originalName": ["\u041c\u043e\u0441\u043a\u0432\u0430"], "city__video": ["watch%3Fv=bsLRYMM3ORs", "watch%3Fv=f9p20dxtTkY"], "city__blankInfo": [45000000], "city__blankName": ["OKTMO ID"], "city__flagSize": [120], "city__governingBody": ["Moscow_City_Duma"], "city__governingBody__homepage": [""], "city__governingBody__lat": [55.76450347900391], "city__governingBody__long": [37.61722183227539], "city__governingBody__subject": ["Category:Moscow_City_Duma", "Category:Legislatures_of_the_federal_subjects_of_Russia"], "city__governingBody__website": [""], "city__governingBody__point": ["55.764503 37.61722"], "city__governingBody__lastElectionDate": [2019], "city__governingBody__coaRes": [110], "city__governingBody__foundation": [1993], "city__governingBody__party": ["United_Russia"], "city__governingBody__nextElection": [2024], "city__governingBody__lastElection": [2019], "city__governingBody__geometry": [null], "city__governingBody__nativeName": ["\u041c\u043e\u0441\u043a\u043e\u0432\u0441\u043a\u0430\u044f \u0433\u043e\u0440\u043e\u0434\u0441\u043a\u0430\u044f \u0434\u0443\u043c\u0430"], "city__governingBody__leader": ["Aleksei_Shaposhnikov_(politician)"], "city__governingBody__meetingPlace": [250], "city__governingBody__votingSystem": ["Plurality_voting"], "city__governingBody__structure1Res": [250], "city__governingBody__precededBy": ["Mossoviet"], "city__governingBody__structure": ["MosGorDuma2019.svg"], "city__governingBody__members": [45], "city__governingBody__houseType": ["Unicameral"], "city__governingBody__politicalGroups": ["", "Government", "Yabloko", "\"My Moscow\"", "United Russia", "Communist Party", "Opposition", "A Just Russia", "Independent"], "city__governingBody__politicalPartyInLegislature": ["Communist_Party_of_the_Russian_Federation", "Yabloko", "A_Just_Russia", "United_Russia", "Independent_politician"], "city__governingBody__termLength": [null], "city__governingBody__politicalPartyOfLeader": ["United_Russia"], "city__governingBody__leader1Type": ["Chairman"], "city__governingBody__numberOfMembers": [45], "city__governingBody__coaPic": ["Moscow City Duma Logo.png"], "city__anthem__country": ["", "the"], "city__anthem__hypernym": ["Anthem"], "city__anthem__bot": ["InternetArchiveBot"], "city__anthem__date": ["January 2018"], "city__anthem__fixAttempted": ["yes"], "city__anthem__prefix": ["Municipal"], "city__isoCodeRegion": ["RU-MOW"], "city__footerAlign": ["center"], "city__isoCode": ["RU-MOW"], "city__content": ["Chart\n | width=400\n | height=200\n | type=area\n | colors=#99B2CC\n | xAxisMin=1350|xAxisMax=2018\n | xAxisTitle=Year\n | x= 1350, 1400, 1600, 1638, 1710, 1725, 1738, 1750, 1775, 1785, 1800, 1811, 1813, 1825, 1830, 1835, 1840, 1847, 1852, 1856, 1858, 1859, 1863, 1864, 1868, 1871, 1886, 1891, 1897, 1900, 1902, 1907, 1908, 1912, 1913, 1914, 1915, 1917, 1920, 1923, 1926, 1928, 1931, 1936, 1939, 1956, 1959, 1967, 1970, 1972, 1973, 1975, 1976, 1979, 1982, 1985, 1986, 1987, 1989, 1990, 1991, 1992, 1993, 1994, 1995, 1996, 1997, 1998, 1999, 2000, 2001, 2002, 2003, 2004, 2005, 2006, 2007, 2008, 2009, 2010, 2011, 2012, 2013, 2014, 2015, 2016, 2018\n | yAxisFormat=s | yGrid= \n | yAxisTitle=Population\n | y= 30000, 40000, 100000, 200000, 160000, 145000, 138400, 130000, 161000, 188700, 250000, 270200, 215000, 241500, 305600, 335800, 349100, 353300, 373800, 368800, 377800, 379300, 462500, 351600, 416400, 601969, 753459, 822400, 1039000, 1175000, 1174700, 1345700, 1359200, 1617157, 1563100, 1762700, 1817000, 1854400, 1028200, 1542900, 2080000, 2127200, 2781300, 3641500, 4131633, 4839000, 5045905, 6422000, 6941961, 7151000, 7255000, 7862000, 7658000, 7830509, 8111000, 8652000, 8527000, 8815000, 8769117, 8880124, 9017415, 9067808, 9066025, 9066612, 9085457, 9246727, 9411236, 9604297, 9783242, 9932932, 10114203, 10269900, 10386903, 10535681, 10726429, 10923762, 11091428, 11186851, 11281631, 11503501, 11776764, 11856578, 11979529, 12108257, 12197596, 12330126, 13010112"], "city__shieldSize": [75], "city__subdivisionType": ["Economic_regions_of_Russia", "Federal_districts_of_Russia", "Country"], "city__subdivisionType__subject": ["Category:Lists_of_subdivisions_of_Russia", "Category:Economic_regions_of_Russia", "Category:Federal_districts_of_Russia", "Category:Political_divisions_of_Russia", "Category:Federalism_in_Russia"], "city__populationAsOf": [2021], "city__subdivisionName": ["Central_economic_region", "Central_Federal_District"], "city__subdivisionName__hypernym": ["Regions", "Districts"], "city__subdivisionName__wikiPageRedirects": ["Central_Economic_Region"], "city__subdivisionName__homepage": [""], "city__subdivisionName__lat": [54.53300094604492], "city__subdivisionName__long": [37.61700057983398], "city__subdivisionName__subject": ["Category:Federal_districts_of_Russia", "Category:2000_establishments_in_Russia", "Category:States_and_territories_established_in_2000", "Category:Central_Federal_District"], "city__subdivisionName__website": [""], "city__subdivisionName__title": ["Baikaland at Tripod.com"], "city__subdivisionName__point": ["54.533 37.617"], "city__subdivisionName__foundingDate": [2000], "city__subdivisionName__nativeNameLang": ["ru"], "city__subdivisionName__populationDensityKm": ["auto"], "city__subdivisionName__originalName": ["\u0426\u0435\u043d\u0442\u0440\u0430\u043b\u044c\u043d\u044b\u0439 \u0444\u0435\u0434\u0435\u0440\u0430\u043b\u044c\u043d\u044b\u0439 \u043e\u043a\u0440\u0443\u0433"], "city__subdivisionName__url": ["cfo.html"], "city__subdivisionName__establishedTitle": ["Established"], "city__subdivisionName__establishedDate": [2000], "city__subdivisionName__seat": ["Moscow"], "city__subdivisionName__seatType": ["Administrative Centre"], "city__subdivisionName__areaRank": [6], "city__subdivisionName__populationUrban": [null, 81], "city__subdivisionName__populationRural": [19, null], "city__subdivisionName__geometry": [null], "city__subdivisionName__subdivisionType": ["Country"], "city__subdivisionName__populationAsOf": [2010], "city__subdivisionName__populationTotal": [38427539], "city__subdivisionName__settlementType": ["Federal district of Russia"], "city__subdivisionName__country": ["Russia"], "city__subdivisionName__unitPref": ["Metric"], "city__subdivisionName__nativeName": ["\u0426\u0435\u043d\u0442\u0440\u0430\u043b\u044c\u043d\u044b\u0439 \u0444\u0435\u0434\u0435\u0440\u0430\u043b\u044c\u043d\u044b\u0439 \u043e\u043a\u0440\u0443\u0433"], "city__subdivisionName__blank1InfoSec": [2], "city__subdivisionName__blank1NameSec": ["Economic regions"], "city__subdivisionName__leaderTitle": ["Presidential Envoy"], "city__subdivisionName__areaTotal": [null, 650200000000], "city__subdivisionName__imageMap": ["Map of Russia - Central Federal District .svg"], "city__subdivisionName__areaTotalKm": [650200], "city__subdivisionName__politicalLeader": ["Central_Federal_District__PoliticalFunction__1"], "city__subdivisionName__leaderName": ["Igor_Shchyogolev"], "city__subdivisionName__blankInfoSec": [0.847, "\u00b7 1st"], "city__subdivisionName__blankNameSec": ["Human_Development_Index", "Federal subjects"], "city__subdivisionName__date": [2007], "city__subdivisionName__populationTotalRanking": [1], "city__subdivisionName__populationRank": [null], "city__subdivisionName__totalType": ["Total"], "city__populationTotal": [13010112], "city__subdivision": ["Central_economic_region", "Central_Federal_District"], "city__subdivision__hypernym": ["Regions", "Districts"], "city__subdivision__wikiPageRedirects": ["Central_Economic_Region"], "city__subdivision__homepage": [""], "city__subdivision__lat": [54.53300094604492], "city__subdivision__long": [37.61700057983398], "city__subdivision__subject": ["Category:Federal_districts_of_Russia", "Category:2000_establishments_in_Russia", "Category:States_and_territories_established_in_2000", "Category:Central_Federal_District"], "city__subdivision__website": [""], "city__subdivision__title": ["Baikaland at Tripod.com"], "city__subdivision__point": ["54.533 37.617"], "city__subdivision__foundingDate": [2000], "city__subdivision__nativeNameLang": ["ru"], "city__subdivision__populationDensityKm": ["auto"], "city__subdivision__originalName": ["\u0426\u0435\u043d\u0442\u0440\u0430\u043b\u044c\u043d\u044b\u0439 \u0444\u0435\u0434\u0435\u0440\u0430\u043b\u044c\u043d\u044b\u0439 \u043e\u043a\u0440\u0443\u0433"], "city__subdivision__url": ["cfo.html"], "city__subdivision__establishedTitle": ["Established"], "city__subdivision__establishedDate": [2000], "city__subdivision__seat": ["Moscow"], "city__subdivision__seatType": ["Administrative Centre"], "city__subdivision__areaRank": [6], "city__subdivision__populationUrban": [null, 81], "city__subdivision__populationRural": [19, null], "city__subdivision__geometry": [null], "city__subdivision__subdivisionType": ["Country"], "city__subdivision__populationAsOf": [2010], "city__subdivision__populationTotal": [38427539], "city__subdivision__settlementType": ["Federal district of Russia"], "city__subdivision__country": ["Russia"], "city__subdivision__unitPref": ["Metric"], "city__subdivision__nativeName": ["\u0426\u0435\u043d\u0442\u0440\u0430\u043b\u044c\u043d\u044b\u0439 \u0444\u0435\u0434\u0435\u0440\u0430\u043b\u044c\u043d\u044b\u0439 \u043e\u043a\u0440\u0443\u0433"], "city__subdivision__blank1InfoSec": [2], "city__subdivision__blank1NameSec": ["Economic regions"], "city__subdivision__leaderTitle": ["Presidential Envoy"], "city__subdivision__areaTotal": [null, 650200000000], "city__subdivision__imageMap": ["Map of Russia - Central Federal District .svg"], "city__subdivision__areaTotalKm": [650200], "city__subdivision__politicalLeader": ["Central_Federal_District__PoliticalFunction__1"], "city__subdivision__leaderName": ["Igor_Shchyogolev"], "city__subdivision__blankInfoSec": [0.847, "\u00b7 1st"], "city__subdivision__blankNameSec": ["Human_Development_Index", "Federal subjects"], "city__subdivision__date": [2007], "city__subdivision__populationTotalRanking": [1], "city__subdivision__populationRank": [null], "city__subdivision__totalType": ["Total"], "city__timeZone": ["Moscow_Time"], "city__timeZone__subject": ["Category:Time_in_Russia", "Category:Time_zones"], "city__timeZone__hypernym": ["Zone"], "city__settlementType": ["Capital city and federal city"], "city__utcOffset": ["+3"], "city__timezone": ["Moscow_Time"], "city__timezone__subject": ["Category:Time_in_Russia", "Category:Time_zones"], "city__timezone__hypernym": ["Zone"], "city__nativeName": ["\u041c\u043e\u0441\u043a\u0432\u0430"], "city__areaTotalSqMi": [989], "city__alt": ["Panorama of Moscow in 1819-1823"], "city__yearHighC": [10.2, 8.9], "city__yearLowC": [1.2, 3.1], "city__yearMeanC": [5, 6.6], "city__registrationPlate": [77177777], "city__leaderTitle__differentFrom": ["Governor_of_Moscow_Oblast"], "city__leaderTitle__seeAlso": ["2018_Moscow_mayoral_election", "Government_of_Moscow", "Russia", "Elections"], "city__demonym": ["Muscovite"], "city__populationDemonym": ["Muscovite"], "city__areaTotalKm": [2561.5], "city__politicalLeader": ["Moscow__PoliticalFunction__1"], "city__politicalLeader__leaderTitle": ["Mayor"], "city__politicalLeader__politician": ["Sergey_Sobyanin"], "city__politicalLeader__personName": ["Sergey Sobyanin"], "city__leaderName__nativeNameLang": ["ru"], "city__leaderName__primeminister": ["Vladimir_Putin"], "city__leaderName__profession": ["Lawyer", "Engineer"], "city__leaderName__signature": ["Signature of Sergey Sobyanin.png"], "city__leaderName__filename": ["Sergej Sobyanin voice.oga"], "city__leaderName__soundRecording": ["Sergey_Sobyanin__Sound__1"], "city__imageShield": ["Coat of Arms of Moscow.svg"], "city__source": ["weatheronline.co.uk"], "city__collapsed": ["yes"], "city__fullwidth": [12569], "city__fullheight": [600], "city__blank6Name": ["Gross_Regional_Product"], "city__blank6Name__hypernym": ["Measures"], "city__blank6Name__wikiPageRedirects": ["Gross_regional_product"], "city__blank6Info": ["\u20bd20 trillion"], "city__shieldLink": ["Coat of arms of Moscow"], "city__decLowC": ["\u22125.4", "\u22128.6"], "city__octLowC": [2, 3.1], "city__janMeanC": ["\u22127.9", "\u22129.3"], "city__metricFirst": ["Yes", "yes"], "city__julMeanC": [20.7, 18.2], "city__mayHighC": [18.4, 20.1], "city__febHighC": ["\u22123.6", "\u22124.2"], "city__octHighC": [8.2, 7.9], "city__sepMeanC": [12.9, 11.1], "city__augHighC": [21.5, 23.9], "city__aprMeanC": [6.9, 5.8], "city__marMeanC": ["\u22122.2", "\u22121.0"], "city__aprHighC": [10.4, 11.4], "city__augSun": [242], "city__junSun": [299], "city__janSun": [37], "city__junHighC": [21.7, 22.6], "city__decMeanC": ["\u22126.1", "\u22123.9"], "city__novLowC": ["\u22120.7", "\u22123.3"], "city__novHighC": [2.1, 1.1], "city__octMeanC": [5.5, 5.1], "city__sepHighC": [16.7, 15.4], "city__febLowC": ["\u221211.1", "\u22128.3"], "city__mayMeanC": [14.7, 13.1], "city__julLowC": [15.6, 13.5], "city__augLowC": [12, 13.8], "city__octSun": [88], "city__aprSun": [213], "city__populationTotalRanking": [1], "city__julSun": [323], "city__novSun": [33], "city__janLowC": ["\u221212.3", "\u22129.7"], "city__sepSun": [171], "city__novMeanC": [0.7, "\u22121.2"], "city__junMeanC": [16.6, 17.6], "city__decHighC": ["\u22122.4", "\u22123.5"], "city__singleLine": ["Yes", "yes"], "city__julHighC": [23.1, 25.8], "city__augMeanC": [18.9, 16.4], "city__aprLowC": [2.3, 1.7], "city__janHighC": ["\u22126.3", "\u22126.0"], "city__populationMetro": [20004462], "city__marHighC": [1.5, 2.4], "city__mapsize": [295], "city__marLowC": ["\u22125.6", "\u22124.5"], "city__sepLowC": [7.1, 9.1], "city__febMeanC": ["\u22127.7", "\u22126.0"], "city__mayLowC": [9.4, 7.6], "city__junLowC": [11.5, 12.5], "city__decSun": [14], "city__populationRank": [null], "city__marSun": [142], "city__maySun": [274], "city__febSun": [65], "city__totalType": ["Total"], "city__flagLink": ["Flag of Moscow"], "artist": ["Nikolai_Tomsky", "V. Bogolubov, Vladimir Ingal"], "artist__subject": ["Category:Heroes_of_Socialist_Labour", "Category:20th-century_sculptors", "Category:1900_births", "Category:Soviet_sculptors", "Category:1984_deaths", "Category:Stalin_Prize_winners", "Category:Full_Members_of_the_USSR_Academy_of_Arts", "Category:Russian_male_sculptors", "Category:People_from_Novgorod_Oblast"], "artist__subject__broader": ["Category:Hero_(title)", "Category:Recipients_of_Soviet_Union_civil_awards_and_decorations", "Category:20th-century_artists", "Category:Sculptors_by_century", "Category:19th-century_births", "Category:20th-century_sculptors", "Category:Sculptures_in_the_Soviet_Union", "Category:Soviet_artists", "Category:Joseph_Stalin", "Category:USSR_Academy_of_Arts", "Category:Soviet_painters", "Category:Academicians_of_the_Russian_Academy_of_Arts_and_its_forerunners", "Category:Academicians_of_the_Soviet_Union", "Category:Russian_sculptors", "Category:Male_sculptors_by_nationality", "Category:Russian_male_artists", "Category:Novgorod_Oblast", "Category:People_by_federal_subject_in_Russia"], "artist__subject__related": ["Category:Recipients_of_the_USSR_State_Prize"], "artist__hypernym": ["Sculptor"], "artist__hypernym__wikiPageRedirects": ["Sculpture"], "year": [1952], "metricUnit": ["cm"], "imperialUnit": ["in"], "backcolor": ["#FBF5DF"], "author": ["Nikolai_Tomsky"], "author__subject": ["Category:Heroes_of_Socialist_Labour", "Category:20th-century_sculptors", "Category:1900_births", "Category:Soviet_sculptors", "Category:1984_deaths", "Category:Stalin_Prize_winners", "Category:Full_Members_of_the_USSR_Academy_of_Arts", "Category:Russian_male_sculptors", "Category:People_from_Novgorod_Oblast"], "author__subject__broader": ["Category:Hero_(title)", "Category:Recipients_of_Soviet_Union_civil_awards_and_decorations", "Category:20th-century_artists", "Category:Sculptors_by_century", "Category:19th-century_births", "Category:20th-century_sculptors", "Category:Sculptures_in_the_Soviet_Union", "Category:Soviet_artists", "Category:Joseph_Stalin", "Category:USSR_Academy_of_Arts", "Category:Soviet_painters", "Category:Academicians_of_the_Russian_Academy_of_Arts_and_its_forerunners", "Category:Academicians_of_the_Soviet_Union", "Category:Russian_sculptors", "Category:Male_sculptors_by_nationality", "Category:Russian_male_artists", "Category:Novgorod_Oblast", "Category:People_by_federal_subject_in_Russia"], "author__subject__related": ["Category:Recipients_of_the_USSR_State_Prize"], "author__hypernym": ["Sculptor"], "author__hypernym__wikiPageRedirects": ["Sculpture"], "imageSize": [220], "paintingAlignment": ["right"]}