{"band_gap": [0.4707], "density": [5.570509], "density_atomic": [23.76389], "deprecated": [false], "efermi": [7.605682], "energy_above_hull": [0.5742827], "energy_per_atom": [-20.51332], "formation_energy_per_atom": [-1.920405], "is_gap_direct": [false], "is_magnetic": [true], "is_metal": [false], "is_stable": [false], "nelements": [3], "nsites": [14], "num_magnetic_sites": [2], "num_unique_magnetic_sites": [1], "theoretical": [true], "total_magnetization": [2.0], "total_magnetization_normalized_formula_units": [0.9999999], "total_magnetization_normalized_vol": [0.006011521], "uncorrected_energy_per_atom": [-20.51332], "volume": [332.6945], "cbm": [7.6057], "vbm": [7.135]}