{"band_gap": [2.074], "density": [5.534941], "density_atomic": [13.86219], "deprecated": [false], "efermi": [2.079199], "energy_above_hull": [9.085125e-05], "energy_per_atom": [-7.391891], "formation_energy_per_atom": [-2.621907], "homogeneous_poisson": [0.361], "is_gap_direct": [false], "is_magnetic": [false], "is_metal": [false], "is_stable": [false], "nelements": [3], "nsites": [4], "num_magnetic_sites": [0], "num_unique_magnetic_sites": [0], "theoretical": [false], "total_magnetization": [0.0], "total_magnetization_normalized_formula_units": [0.0], "total_magnetization_normalized_vol": [0.0], "uncorrected_energy_per_atom": [-13.67767], "universal_anisotropy": [5.876], "volume": [55.44877], "cbm": [4.0538], "vbm": [1.9798]}