{"band_gap": [1.459], "density": [7.266372], "density_atomic": [26.49322], "deprecated": [false], "efermi": [3.981242], "energy_above_hull": [0.02480869], "energy_per_atom": [-26.35628], "formation_energy_per_atom": [-1.732364], "is_gap_direct": [false], "is_magnetic": [false], "is_metal": [false], "is_stable": [false], "nelements": [3], "nsites": [14], "num_magnetic_sites": [0], "num_unique_magnetic_sites": [0], "theoretical": [true], "total_magnetization": [0.0001005], "total_magnetization_normalized_formula_units": [5.025e-05], "total_magnetization_normalized_vol": [2.709588e-07], "uncorrected_energy_per_atom": [-5.369496], "volume": [370.9051], "cbm": [5.5314], "vbm": [4.0724]}