{"band_gap": [1.2994], "density": [5.870987], "density_atomic": [27.04523], "deprecated": [false], "efermi": [2.840135], "energy_above_hull": [0.0], "energy_per_atom": [-4.351779], "formation_energy_per_atom": [-0.6035621], "is_gap_direct": [false], "is_magnetic": [false], "is_metal": [false], "is_stable": [true], "nelements": [4], "nsites": [16], "num_magnetic_sites": [0], "num_unique_magnetic_sites": [0], "theoretical": [false], "total_magnetization": [0.0032193], "total_magnetization_normalized_formula_units": [0.00160965], "total_magnetization_normalized_vol": [7.439621e-06], "uncorrected_energy_per_atom": [-4.100279], "volume": [432.7236], "cbm": [4.0902], "e_electronic": [6.478347], "e_ionic": [22.13559], "e_total": [28.61393], "equilibrium_reaction_energy_per_atom": [-0.02748617], "n": [2.54526], "vbm": [2.7908]}