{"band_gap": [2.2063], "density": [9.06712], "density_atomic": [12.69991], "deprecated": [false], "efermi": [1.777655], "is_gap_direct": [false], "is_magnetic": [false], "is_metal": [false], "is_stable": [false], "nelements": [3], "nsites": [6], "num_magnetic_sites": [0], "num_unique_magnetic_sites": [0], "theoretical": [true], "total_magnetization": [0.0003464], "total_magnetization_normalized_formula_units": [0.0001732], "total_magnetization_normalized_vol": [4.545963e-06], "volume": [76.19948], "cbm": [3.9323], "vbm": [1.726]}