{"band_gap": [0.0], "density": [11.14286], "density_atomic": [32.0788], "deprecated": [false], "efermi": [6.776313], "energy_above_hull": [0.04728065], "energy_per_atom": [-63.2795], "formation_energy_per_atom": [0.04728065], "homogeneous_poisson": [0.235], "is_gap_direct": [false], "is_magnetic": [false], "is_metal": [true], "is_stable": [false], "nelements": [2], "nsites": [4], "num_magnetic_sites": [0], "num_unique_magnetic_sites": [0], "theoretical": [true], "total_magnetization": [0.0017919], "total_magnetization_normalized_formula_units": [0.0017919], "total_magnetization_normalized_vol": [1.396483e-05], "uncorrected_energy_per_atom": [-63.2795], "universal_anisotropy": [0.782], "volume": [128.3152]}