{"band_gap": [3.9015], "density": [2.623345], "density_atomic": [22.92237], "deprecated": [false], "efermi": [0.01911985], "energy_above_hull": [0.0239996], "energy_per_atom": [-7.202611], "formation_energy_per_atom": [-0.726957], "is_gap_direct": [false], "is_magnetic": [false], "is_metal": [false], "is_stable": [false], "nelements": [4], "nsites": [14], "num_magnetic_sites": [0], "num_unique_magnetic_sites": [0], "theoretical": [false], "total_magnetization": [0.0015132], "total_magnetization_normalized_formula_units": [0.0007566], "total_magnetization_normalized_vol": [4.715293e-06], "uncorrected_energy_per_atom": [-6.955754], "volume": [320.9132], "cbm": [3.8362], "vbm": [-0.0653]}