{"band_gap": [5.0802], "density": [1.639545], "density_atomic": [10.06834], "deprecated": [false], "efermi": [-1.04114], "energy_above_hull": [0.01306092], "energy_per_atom": [-6.211922], "formation_energy_per_atom": [-1.199834], "is_gap_direct": [false], "is_magnetic": [false], "is_metal": [false], "is_stable": [false], "nelements": [6], "nsites": [64], "num_magnetic_sites": [0], "num_unique_magnetic_sites": [0], "theoretical": [false], "total_magnetization": [0.0007607], "total_magnetization_normalized_formula_units": [0.000190175], "total_magnetization_normalized_vol": [1.180526e-06], "uncorrected_energy_per_atom": [-5.986547], "volume": [644.3739], "cbm": [4.0167], "vbm": [-1.0635]}