{"band_gap": [0.0], "density": [13.29363], "density_atomic": [13.24355], "deprecated": [false], "efermi": [7.091368], "energy_above_hull": [0.0], "energy_per_atom": [-29.04442], "formation_energy_per_atom": [-1.020856], "homogeneous_poisson": [0.22], "is_gap_direct": [false], "is_magnetic": [false], "is_metal": [true], "is_stable": [true], "nelements": [3], "nsites": [4], "num_magnetic_sites": [0], "num_unique_magnetic_sites": [0], "theoretical": [true], "total_magnetization": [5.3e-06], "total_magnetization_normalized_formula_units": [5.3e-06], "total_magnetization_normalized_vol": [1.000487e-07], "uncorrected_energy_per_atom": [-29.04442], "universal_anisotropy": [-5.07], "volume": [52.97418], "equilibrium_reaction_energy_per_atom": [-0.1278989]}