{"band_gap": [0.0], "density": [7.458852], "density_atomic": [11.54513], "deprecated": [false], "efermi": [7.030869], "energy_above_hull": [0.0], "energy_per_atom": [-16.84942], "formation_energy_per_atom": [-0.8092044], "homogeneous_poisson": [0.2], "is_gap_direct": [false], "is_magnetic": [false], "is_metal": [true], "is_stable": [true], "nelements": [2], "nsites": [4], "num_magnetic_sites": [0], "num_unique_magnetic_sites": [0], "theoretical": [false], "total_magnetization": [9e-07], "total_magnetization_normalized_formula_units": [4.5e-07], "total_magnetization_normalized_vol": [1.948874e-08], "uncorrected_energy_per_atom": [-16.84942], "universal_anisotropy": [0.076], "volume": [46.1805], "equilibrium_reaction_energy_per_atom": [-0.05023144]}