{"band_gap": [0.0], "density": [10.00915], "density_atomic": [14.26661], "deprecated": [false], "efermi": [8.313418], "energy_above_hull": [0.0], "energy_per_atom": [-6.968789], "formation_energy_per_atom": [-0.2341947], "is_gap_direct": [false], "is_magnetic": [false], "is_metal": [true], "is_stable": [true], "nelements": [2], "nsites": [6], "num_magnetic_sites": [0], "num_unique_magnetic_sites": [0], "theoretical": [false], "total_magnetization": [0.0001355], "total_magnetization_normalized_formula_units": [6.775e-05], "total_magnetization_normalized_vol": [1.58295e-06], "uncorrected_energy_per_atom": [-19.14603], "volume": [85.59965], "equilibrium_reaction_energy_per_atom": [-0.2341947]}