{"band_gap": [5.4269], "density": [2.679633], "density_atomic": [9.591801], "deprecated": [false], "efermi": [1.333456], "energy_above_hull": [0.01867461], "energy_per_atom": [-7.648149], "formation_energy_per_atom": [-2.719929], "is_gap_direct": [false], "is_magnetic": [false], "is_metal": [false], "is_stable": [false], "nelements": [3], "nsites": [117], "num_magnetic_sites": [0], "num_unique_magnetic_sites": [0], "theoretical": [false], "total_magnetization": [0.0003349], "total_magnetization_normalized_formula_units": [3.721111e-05], "total_magnetization_normalized_vol": [2.984208e-07], "uncorrected_energy_per_atom": [-7.278226], "volume": [1122.241], "cbm": [6.6646], "vbm": [1.2377]}