{"band_gap": [0.0], "density": [4.668837], "density_atomic": [14.11609], "deprecated": [false], "efermi": [7.451083], "energy_above_hull": [0.03314315], "energy_per_atom": [-11.01683], "formation_energy_per_atom": [-0.7657195], "homogeneous_poisson": [0.162], "is_gap_direct": [false], "is_magnetic": [true], "is_metal": [true], "is_stable": [false], "nelements": [2], "nsites": [6], "num_magnetic_sites": [2], "num_unique_magnetic_sites": [1], "theoretical": [false], "total_magnetization": [1.968753], "total_magnetization_normalized_formula_units": [0.9843766], "total_magnetization_normalized_vol": [0.02324479], "uncorrected_energy_per_atom": [-6.332682], "universal_anisotropy": [0.595], "volume": [84.69654]}