{"band_gap": [0.0], "density": [5.1934], "density_atomic": [33.33912], "deprecated": [false], "efermi": [3.27921], "energy_above_hull": [0.07355722], "energy_per_atom": [-22.59487], "formation_energy_per_atom": [0.07355722], "is_gap_direct": [false], "is_magnetic": [false], "is_metal": [true], "is_stable": [false], "nelements": [2], "nsites": [4], "num_magnetic_sites": [0], "num_unique_magnetic_sites": [0], "theoretical": [true], "total_magnetization": [3e-07], "total_magnetization_normalized_formula_units": [3e-07], "total_magnetization_normalized_vol": [2.249609e-09], "uncorrected_energy_per_atom": [-22.59487], "volume": [133.3565]}