{"band_gap": [0.0], "density": [2.547099], "density_atomic": [26.21063], "deprecated": [false], "efermi": [3.293979], "energy_above_hull": [0.02138946], "energy_per_atom": [-10.3627], "formation_energy_per_atom": [-1.587241], "homogeneous_poisson": [0.318], "is_gap_direct": [false], "is_magnetic": [true], "is_metal": [true], "is_stable": [false], "nelements": [2], "nsites": [4], "num_magnetic_sites": [2], "num_unique_magnetic_sites": [1], "theoretical": [false], "total_magnetization": [1.552691], "total_magnetization_normalized_formula_units": [0.7763456], "total_magnetization_normalized_vol": [0.01480974], "uncorrected_energy_per_atom": [-5.515481], "universal_anisotropy": [-18.815], "volume": [104.8425]}