{"band_gap": [0.0], "density": [3.962325], "density_atomic": [20.30462], "deprecated": [false], "efermi": [4.209385], "energy_above_hull": [0.02618649], "energy_per_atom": [-11.97686], "formation_energy_per_atom": [-0.1194412], "is_gap_direct": [false], "is_magnetic": [true], "is_metal": [true], "is_stable": [false], "nelements": [2], "nsites": [32], "num_magnetic_sites": [8], "num_unique_magnetic_sites": [2], "theoretical": [false], "total_magnetization": [2.241953], "total_magnetization_normalized_formula_units": [0.2802441], "total_magnetization_normalized_vol": [0.003450496], "uncorrected_energy_per_atom": [-11.97686], "volume": [649.7478]}