{"band_gap": [0.0], "density": [9.215206], "density_atomic": [11.47996], "deprecated": [false], "efermi": [5.530327], "energy_above_hull": [0.0], "energy_per_atom": [-8.148151], "formation_energy_per_atom": [-0.2858914], "is_gap_direct": [false], "is_magnetic": [true], "is_metal": [true], "is_stable": [true], "nelements": [3], "nsites": [4], "num_magnetic_sites": [1], "num_unique_magnetic_sites": [1], "theoretical": [false], "total_magnetization": [1.678359], "total_magnetization_normalized_formula_units": [1.678359], "total_magnetization_normalized_vol": [0.03654974], "uncorrected_energy_per_atom": [-18.40154], "volume": [45.91984], "equilibrium_reaction_energy_per_atom": [-0.004441725]}