{"band_gap": [1.9603], "density": [4.315733], "density_atomic": [13.00252], "deprecated": [false], "efermi": [1.727644], "energy_above_hull": [0.522215], "energy_per_atom": [-11.07945], "formation_energy_per_atom": [-1.996743], "is_gap_direct": [false], "is_magnetic": [false], "is_metal": [false], "is_stable": [false], "nelements": [3], "nsites": [18], "num_magnetic_sites": [0], "num_unique_magnetic_sites": [0], "theoretical": [true], "total_magnetization": [0.001005], "total_magnetization_normalized_formula_units": [0.0005025], "total_magnetization_normalized_vol": [4.294039e-06], "uncorrected_energy_per_atom": [-7.18153], "volume": [234.0454], "cbm": [3.7519], "vbm": [1.7916]}