{"band_gap": [5.5869], "density": [1.850177], "density_atomic": [17.97528], "deprecated": [false], "efermi": [-1.313347], "energy_above_hull": [0.04101364], "energy_per_atom": [-9.90316], "formation_energy_per_atom": [-3.004804], "is_gap_direct": [false], "is_magnetic": [false], "is_metal": [false], "is_stable": [false], "nelements": [2], "nsites": [72], "num_magnetic_sites": [0], "num_unique_magnetic_sites": [0], "theoretical": [true], "total_magnetization": [0.0], "total_magnetization_normalized_formula_units": [0.0], "total_magnetization_normalized_vol": [0.0], "uncorrected_energy_per_atom": [-9.90316], "volume": [1294.22], "cbm": [4.3036], "vbm": [-1.2833]}