{"band_gap": [0.0], "density": [14.02375], "density_atomic": [23.92244], "deprecated": [false], "efermi": [6.565928], "energy_above_hull": [0.2441617], "energy_per_atom": [-5.009219], "formation_energy_per_atom": [-0.05340727], "is_gap_direct": [false], "is_magnetic": [false], "is_metal": [true], "is_stable": [false], "nelements": [2], "nsites": [4], "num_magnetic_sites": [0], "num_unique_magnetic_sites": [0], "theoretical": [true], "total_magnetization": [0.0009827], "total_magnetization_normalized_formula_units": [0.00049135], "total_magnetization_normalized_vol": [1.026964e-05], "uncorrected_energy_per_atom": [-5.009219], "volume": [95.68978]}