{"band_gap": [0.0], "density": [5.968169], "density_atomic": [14.1539], "deprecated": [false], "efermi": [4.75887], "energy_above_hull": [0.6950094], "energy_per_atom": [-7.447427], "formation_energy_per_atom": [0.4116848], "is_gap_direct": [false], "is_magnetic": [true], "is_metal": [true], "is_stable": [false], "nelements": [2], "nsites": [5], "num_magnetic_sites": [4], "num_unique_magnetic_sites": [2], "theoretical": [true], "total_magnetization": [9.448259], "total_magnetization_normalized_formula_units": [9.448259], "total_magnetization_normalized_vol": [0.1335075], "uncorrected_energy_per_atom": [-7.447427], "volume": [70.76951]}