{"band_gap": [1.2103], "density": [2.434144], "density_atomic": [14.23231], "deprecated": [false], "efermi": [-1.203683], "energy_above_hull": [0.2008558], "energy_per_atom": [-5.807742], "formation_energy_per_atom": [0.2008558], "is_gap_direct": [false], "is_magnetic": [false], "is_metal": [false], "is_stable": [false], "nelements": [2], "nsites": [16], "num_magnetic_sites": [0], "num_unique_magnetic_sites": [0], "theoretical": [false], "total_magnetization": [0.0], "total_magnetization_normalized_formula_units": [0.0], "total_magnetization_normalized_vol": [0.0], "uncorrected_energy_per_atom": [-5.807742], "volume": [227.7169], "cbm": [-0.166], "e_electronic": [4.137793], "e_ionic": [10.29521], "e_total": [14.433], "n": [2.034156], "vbm": [-1.3763], "e_ij_max": [1.718483]}