{"band_gap": [5.0727], "density": [1.795044], "density_atomic": [8.149209], "deprecated": [false], "efermi": [-0.7027646], "energy_above_hull": [0.0], "energy_per_atom": [-5.604467], "formation_energy_per_atom": [-1.085447], "is_gap_direct": [true], "is_magnetic": [false], "is_metal": [false], "is_stable": [true], "nelements": [4], "nsites": [60], "num_magnetic_sites": [0], "num_unique_magnetic_sites": [0], "theoretical": [false], "total_magnetization": [0.576803], "total_magnetization_normalized_formula_units": [0.1442007], "total_magnetization_normalized_vol": [0.001179671], "uncorrected_energy_per_atom": [-5.373133], "volume": [488.9525], "cbm": [4.3043], "e_electronic": [2.294208], "e_ionic": [4.061528], "e_total": [6.355737], "equilibrium_reaction_energy_per_atom": [-0.02870226], "n": [1.514664], "vbm": [-0.7684], "e_ij_max": [0.1782691]}