{"band_gap": [1.4357], "density": [3.567285], "density_atomic": [29.22235], "deprecated": [false], "efermi": [1.640173], "energy_above_hull": [0.6283472], "energy_per_atom": [-4.260201], "formation_energy_per_atom": [0.4921285], "is_gap_direct": [false], "is_magnetic": [false], "is_metal": [false], "is_stable": [false], "nelements": [3], "nsites": [20], "num_magnetic_sites": [0], "num_unique_magnetic_sites": [0], "theoretical": [false], "total_magnetization": [0.0017085], "total_magnetization_normalized_formula_units": [0.000427125], "total_magnetization_normalized_vol": [2.923276e-06], "uncorrected_energy_per_atom": [-4.115801], "volume": [584.447], "cbm": [3.018], "vbm": [1.5823]}